<HealthData locale="en_AR">
 <ExportDate value="2016-04-16 21:27:12 -0300"/>
 <Me HKCharacteristicTypeIdentifierDateOfBirth="1981-03-04" HKCharacteristicTypeIdentifierBiologicalSex="HKBiologicalSexMale" HKCharacteristicTypeIdentifierBloodType="HKBloodTypeNotSet" HKCharacteristicTypeIdentifierFitzpatrickSkinType="HKFitzpatrickSkinTypeNotSet"/>
  <Record type="HKQuantityTypeIdentifierHeartRate" sourceName="Nicolas's Apple Watch" sourceVersion="2.2" device="&lt;&lt;HKDevice: 0x140c955a0&gt;, name:Apple Watch, manufacturer:Apple, model:Watch, hardware:Watch1,2, software:2.2&gt;" unit="count/min" creationDate="2016-04-16 10:31:55 -0300" startDate="2016-04-16 10:31:55 -0300" endDate="2016-04-16 10:31:55 -0300" value="149"/>
 <Record type="HKQuantityTypeIdentifierHeartRate" sourceName="Nicolas's Apple Watch" sourceVersion="2.2" device="&lt;&lt;HKDevice: 0x140c95800&gt;, name:Apple Watch, manufacturer:Apple, model:Watch, hardware:Watch1,2, software:2.2&gt;" unit="count/min" creationDate="2016-04-16 10:32:00 -0300" startDate="2016-04-16 10:32:00 -0300" endDate="2016-04-16 10:32:00 -0300" value="148"/>
 <Record type="HKQuantityTypeIdentifierHeartRate" sourceName="Nicolas's Apple Watch" sourceVersion="2.2" device="&lt;&lt;HKDevice: 0x140c95a60&gt;, name:Apple Watch, manufacturer:Apple, model:Watch, hardware:Watch1,2, software:2.2&gt;" unit="count/min" creationDate="2016-04-16 10:32:05 -0300" startDate="2016-04-16 10:32:05 -0300" endDate="2016-04-16 10:32:05 -0300" value="139"/>
 <Record type="HKQuantityTypeIdentifierHeartRate" sourceName="Nicolas's Apple Watch" sourceVersion="2.2" device="&lt;&lt;HKDevice: 0x140c95cc0&gt;, name:Apple Watch, manufacturer:Apple, model:Watch, hardware:Watch1,2, software:2.2&gt;" unit="count/min" creationDate="2016-04-16 10:32:10 -0300" startDate="2016-04-16 10:32:10 -0300" endDate="2016-04-16 10:32:10 -0300" value="139"/>
 <Record type="HKQuantityTypeIdentifierHeartRate" sourceName="Nicolas's Apple Watch" sourceVersion="2.2" device="&lt;&lt;HKDevice: 0x140c95f20&gt;, name:Apple Watch, manufacturer:Apple, model:Watch, hardware:Watch1,2, software:2.2&gt;" unit="count/min" creationDate="2016-04-16 10:32:15 -0300" startDate="2016-04-16 10:32:15 -0300" endDate="2016-04-16 10:32:15 -0300" value="139"/>
 <Record type="HKQuantityTypeIdentifierHeartRate" sourceName="Nicolas's Apple Watch" sourceVersion="2.2" device="&lt;&lt;HKDevice: 0x140c96180&gt;, name:Apple Watch, manufacturer:Apple, model:Watch, hardware:Watch1,2, software:2.2&gt;" unit="count/min" creationDate="2016-04-16 10:32:20 -0300" startDate="2016-04-16 10:32:20 -0300" endDate="2016-04-16 10:32:20 -0300" value="139"/>
 <Record type="HKQuantityTypeIdentifierHeartRate" sourceName="Nicolas's Apple Watch" sourceVersion="2.2" device="&lt;&lt;HKDevice: 0x140c963e0&gt;, name:Apple Watch, manufacturer:Apple, model:Watch, hardware:Watch1,2, software:2.2&gt;" unit="count/min" creationDate="2016-04-16 10:32:25 -0300" startDate="2016-04-16 10:32:25 -0300" endDate="2016-04-16 10:32:25 -0300" value="137"/>
 <Record type="HKQuantityTypeIdentifierHeartRate" sourceName="Nicolas's Apple Watch" sourceVersion="2.2" device="&lt;&lt;HKDevice: 0x140c96640&gt;, name:Apple Watch, manufacturer:Apple, model:Watch, hardware:Watch1,2, software:2.2&gt;" unit="count/min" creationDate="2016-04-16 10:32:30 -0300" startDate="2016-04-16 10:32:30 -0300" endDate="2016-04-16 10:32:30 -0300" value="138"/>
 <Record type="HKQuantityTypeIdentifierHeartRate" sourceName="Nicolas's Apple Watch" sourceVersion="2.2" device="&lt;&lt;HKDevice: 0x140c968a0&gt;, name:Apple Watch, manufacturer:Apple, model:Watch, hardware:Watch1,2, software:2.2&gt;" unit="count/min" creationDate="2016-04-16 10:32:35 -0300" startDate="2016-04-16 10:32:35 -0300" endDate="2016-04-16 10:32:35 -0300" value="138"/>
 <Record type="HKQuantityTypeIdentifierHeartRate" sourceName="Nicolas's Apple Watch" sourceVersion="2.2" device="&lt;&lt;HKDevice: 0x140c96b00&gt;, name:Apple Watch, manufacturer:Apple, model:Watch, hardware:Watch1,2, software:2.2&gt;" unit="count/min" creationDate="2016-04-16 10:32:40 -0300" startDate="2016-04-16 10:32:40 -0300" endDate="2016-04-16 10:32:40 -0300" value="133"/>
 <Record type="HKQuantityTypeIdentifierHeartRate" sourceName="Nicolas's Apple Watch" sourceVersion="2.2" device="&lt;&lt;HKDevice: 0x140c96d60&gt;, name:Apple Watch, manufacturer:Apple, model:Watch, hardware:Watch1,2, software:2.2&gt;" unit="count/min" creationDate="2016-04-16 10:32:45 -0300" startDate="2016-04-16 10:32:45 -0300" endDate="2016-04-16 10:32:45 -0300" value="133"/>
 <Record type="HKQuantityTypeIdentifierHeartRate" sourceName="Nicolas's Apple Watch" sourceVersion="2.2" device="&lt;&lt;HKDevice: 0x140c96fc0&gt;, name:Apple Watch, manufacturer:Apple, model:Watch, hardware:Watch1,2, software:2.2&gt;" unit="count/min" creationDate="2016-04-16 10:32:50 -0300" startDate="2016-04-16 10:32:50 -0300" endDate="2016-04-16 10:32:50 -0300" value="133"/>
 <Record type="HKQuantityTypeIdentifierHeartRate" sourceName="Nicolas's Apple Watch" sourceVersion="2.2" device="&lt;&lt;HKDevice: 0x140c97220&gt;, name:Apple Watch, manufacturer:Apple, model:Watch, hardware:Watch1,2, software:2.2&gt;" unit="count/min" creationDate="2016-04-16 10:32:55 -0300" startDate="2016-04-16 10:32:55 -0300" endDate="2016-04-16 10:32:55 -0300" value="133"/>
 <Record type="HKQuantityTypeIdentifierHeartRate" sourceName="Nicolas's Apple Watch" sourceVersion="2.2" device="&lt;&lt;HKDevice: 0x140c97480&gt;, name:Apple Watch, manufacturer:Apple, model:Watch, hardware:Watch1,2, software:2.2&gt;" unit="count/min" creationDate="2016-04-16 10:33:00 -0300" startDate="2016-04-16 10:33:00 -0300" endDate="2016-04-16 10:33:00 -0300" value="132"/>
 <Record type="HKQuantityTypeIdentifierHeartRate" sourceName="Nicolas's Apple Watch" sourceVersion="2.2" device="&lt;&lt;HKDevice: 0x140c976e0&gt;, name:Apple Watch, manufacturer:Apple, model:Watch, hardware:Watch1,2, software:2.2&gt;" unit="count/min" creationDate="2016-04-16 10:33:05 -0300" startDate="2016-04-16 10:33:05 -0300" endDate="2016-04-16 10:33:05 -0300" value="134"/>
 <Record type="HKQuantityTypeIdentifierHeartRate" sourceName="Nicolas's Apple Watch" sourceVersion="2.2" device="&lt;&lt;HKDevice: 0x140c97940&gt;, name:Apple Watch, manufacturer:Apple, model:Watch, hardware:Watch1,2, software:2.2&gt;" unit="count/min" creationDate="2016-04-16 10:33:10 -0300" startDate="2016-04-16 10:33:10 -0300" endDate="2016-04-16 10:33:10 -0300" value="133"/>
 <Record type="HKQuantityTypeIdentifierHeartRate" sourceName="Nicolas's Apple Watch" sourceVersion="2.2" device="&lt;&lt;HKDevice: 0x140c97ba0&gt;, name:Apple Watch, manufacturer:Apple, model:Watch, hardware:Watch1,2, software:2.2&gt;" unit="count/min" creationDate="2016-04-16 10:33:15 -0300" startDate="2016-04-16 10:33:15 -0300" endDate="2016-04-16 10:33:15 -0300" value="134"/>
 <Record type="HKQuantityTypeIdentifierHeartRate" sourceName="Nicolas's Apple Watch" sourceVersion="2.2" device="&lt;&lt;HKDevice: 0x140c97e00&gt;, name:Apple Watch, manufacturer:Apple, model:Watch, hardware:Watch1,2, software:2.2&gt;" unit="count/min" creationDate="2016-04-16 10:33:20 -0300" startDate="2016-04-16 10:33:20 -0300" endDate="2016-04-16 10:33:20 -0300" value="135"/>
 <Record type="HKQuantityTypeIdentifierHeartRate" sourceName="Nicolas's Apple Watch" sourceVersion="2.2" device="&lt;&lt;HKDevice: 0x140c98060&gt;, name:Apple Watch, manufacturer:Apple, model:Watch, hardware:Watch1,2, software:2.2&gt;" unit="count/min" creationDate="2016-04-16 10:33:25 -0300" startDate="2016-04-16 10:33:25 -0300" endDate="2016-04-16 10:33:25 -0300" value="140"/>
 <Record type="HKQuantityTypeIdentifierHeartRate" sourceName="Nicolas's Apple Watch" sourceVersion="2.2" device="&lt;&lt;HKDevice: 0x140c982c0&gt;, name:Apple Watch, manufacturer:Apple, model:Watch, hardware:Watch1,2, software:2.2&gt;" unit="count/min" creationDate="2016-04-16 10:33:30 -0300" startDate="2016-04-16 10:33:30 -0300" endDate="2016-04-16 10:33:30 -0300" value="138"/>
 <Record type="HKQuantityTypeIdentifierHeartRate" sourceName="Nicolas's Apple Watch" sourceVersion="2.2" device="&lt;&lt;HKDevice: 0x140c98520&gt;, name:Apple Watch, manufacturer:Apple, model:Watch, hardware:Watch1,2, software:2.2&gt;" unit="count/min" creationDate="2016-04-16 10:33:35 -0300" startDate="2016-04-16 10:33:35 -0300" endDate="2016-04-16 10:33:35 -0300" value="133"/>
 <Record type="HKQuantityTypeIdentifierHeartRate" sourceName="Nicolas's Apple Watch" sourceVersion="2.2" device="&lt;&lt;HKDevice: 0x140c98780&gt;, name:Apple Watch, manufacturer:Apple, model:Watch, hardware:Watch1,2, software:2.2&gt;" unit="count/min" creationDate="2016-04-16 10:33:41 -0300" startDate="2016-04-16 10:33:40 -0300" endDate="2016-04-16 10:33:40 -0300" value="139"/>
 <Record type="HKQuantityTypeIdentifierHeartRate" sourceName="Nicolas's Apple Watch" sourceVersion="2.2" device="&lt;&lt;HKDevice: 0x140c989e0&gt;, name:Apple Watch, manufacturer:Apple, model:Watch, hardware:Watch1,2, software:2.2&gt;" unit="count/min" creationDate="2016-04-16 10:33:45 -0300" startDate="2016-04-16 10:33:45 -0300" endDate="2016-04-16 10:33:45 -0300" value="138"/>
 <Record type="HKQuantityTypeIdentifierHeartRate" sourceName="Nicolas's Apple Watch" sourceVersion="2.2" device="&lt;&lt;HKDevice: 0x140c98c40&gt;, name:Apple Watch, manufacturer:Apple, model:Watch, hardware:Watch1,2, software:2.2&gt;" unit="count/min" creationDate="2016-04-16 10:33:50 -0300" startDate="2016-04-16 10:33:50 -0300" endDate="2016-04-16 10:33:50 -0300" value="132"/>
 <Record type="HKQuantityTypeIdentifierHeartRate" sourceName="Nicolas's Apple Watch" sourceVersion="2.2" device="&lt;&lt;HKDevice: 0x140c98ea0&gt;, name:Apple Watch, manufacturer:Apple, model:Watch, hardware:Watch1,2, software:2.2&gt;" unit="count/min" creationDate="2016-04-16 10:33:55 -0300" startDate="2016-04-16 10:33:55 -0300" endDate="2016-04-16 10:33:55 -0300" value="134"/>
 <Record type="HKQuantityTypeIdentifierHeartRate" sourceName="Nicolas's Apple Watch" sourceVersion="2.2" device="&lt;&lt;HKDevice: 0x140c99100&gt;, name:Apple Watch, manufacturer:Apple, model:Watch, hardware:Watch1,2, software:2.2&gt;" unit="count/min" creationDate="2016-04-16 10:34:00 -0300" startDate="2016-04-16 10:34:00 -0300" endDate="2016-04-16 10:34:00 -0300" value="134"/>
 <Record type="HKQuantityTypeIdentifierHeartRate" sourceName="Nicolas's Apple Watch" sourceVersion="2.2" device="&lt;&lt;HKDevice: 0x140c99360&gt;, name:Apple Watch, manufacturer:Apple, model:Watch, hardware:Watch1,2, software:2.2&gt;" unit="count/min" creationDate="2016-04-16 10:34:05 -0300" startDate="2016-04-16 10:34:05 -0300" endDate="2016-04-16 10:34:05 -0300" value="133"/>
 <Record type="HKQuantityTypeIdentifierHeartRate" sourceName="Nicolas's Apple Watch" sourceVersion="2.2" device="&lt;&lt;HKDevice: 0x140c995c0&gt;, name:Apple Watch, manufacturer:Apple, model:Watch, hardware:Watch1,2, software:2.2&gt;" unit="count/min" creationDate="2016-04-16 10:34:10 -0300" startDate="2016-04-16 10:34:10 -0300" endDate="2016-04-16 10:34:10 -0300" value="135"/>
 <Record type="HKQuantityTypeIdentifierHeartRate" sourceName="Nicolas's Apple Watch" sourceVersion="2.2" device="&lt;&lt;HKDevice: 0x140c99820&gt;, name:Apple Watch, manufacturer:Apple, model:Watch, hardware:Watch1,2, software:2.2&gt;" unit="count/min" creationDate="2016-04-16 10:34:15 -0300" startDate="2016-04-16 10:34:15 -0300" endDate="2016-04-16 10:34:15 -0300" value="138"/>
 <Record type="HKQuantityTypeIdentifierHeartRate" sourceName="Nicolas's Apple Watch" sourceVersion="2.2" device="&lt;&lt;HKDevice: 0x140c99a80&gt;, name:Apple Watch, manufacturer:Apple, model:Watch, hardware:Watch1,2, software:2.2&gt;" unit="count/min" creationDate="2016-04-16 10:34:20 -0300" startDate="2016-04-16 10:34:20 -0300" endDate="2016-04-16 10:34:20 -0300" value="137"/>
 <Record type="HKQuantityTypeIdentifierHeartRate" sourceName="Nicolas's Apple Watch" sourceVersion="2.2" device="&lt;&lt;HKDevice: 0x140c99ce0&gt;, name:Apple Watch, manufacturer:Apple, model:Watch, hardware:Watch1,2, software:2.2&gt;" unit="count/min" creationDate="2016-04-16 10:34:25 -0300" startDate="2016-04-16 10:34:25 -0300" endDate="2016-04-16 10:34:25 -0300" value="138"/>
 <Record type="HKQuantityTypeIdentifierHeartRate" sourceName="Nicolas's Apple Watch" sourceVersion="2.2" device="&lt;&lt;HKDevice: 0x140c99f40&gt;, name:Apple Watch, manufacturer:Apple, model:Watch, hardware:Watch1,2, software:2.2&gt;" unit="count/min" creationDate="2016-04-16 10:34:30 -0300" startDate="2016-04-16 10:34:30 -0300" endDate="2016-04-16 10:34:30 -0300" value="140"/>
 <Record type="HKQuantityTypeIdentifierHeartRate" sourceName="Nicolas's Apple Watch" sourceVersion="2.2" device="&lt;&lt;HKDevice: 0x140c9a1a0&gt;, name:Apple Watch, manufacturer:Apple, model:Watch, hardware:Watch1,2, software:2.2&gt;" unit="count/min" creationDate="2016-04-16 10:34:35 -0300" startDate="2016-04-16 10:34:35 -0300" endDate="2016-04-16 10:34:35 -0300" value="140"/>
 <Record type="HKQuantityTypeIdentifierHeartRate" sourceName="Nicolas's Apple Watch" sourceVersion="2.2" device="&lt;&lt;HKDevice: 0x140c9a400&gt;, name:Apple Watch, manufacturer:Apple, model:Watch, hardware:Watch1,2, software:2.2&gt;" unit="count/min" creationDate="2016-04-16 10:34:40 -0300" startDate="2016-04-16 10:34:40 -0300" endDate="2016-04-16 10:34:40 -0300" value="138"/>
 <Record type="HKQuantityTypeIdentifierHeartRate" sourceName="Nicolas's Apple Watch" sourceVersion="2.2" device="&lt;&lt;HKDevice: 0x140c9a660&gt;, name:Apple Watch, manufacturer:Apple, model:Watch, hardware:Watch1,2, software:2.2&gt;" unit="count/min" creationDate="2016-04-16 10:34:45 -0300" startDate="2016-04-16 10:34:45 -0300" endDate="2016-04-16 10:34:45 -0300" value="138"/>
 <Record type="HKQuantityTypeIdentifierHeartRate" sourceName="Nicolas's Apple Watch" sourceVersion="2.2" device="&lt;&lt;HKDevice: 0x140c9a8c0&gt;, name:Apple Watch, manufacturer:Apple, model:Watch, hardware:Watch1,2, software:2.2&gt;" unit="count/min" creationDate="2016-04-16 10:34:50 -0300" startDate="2016-04-16 10:34:50 -0300" endDate="2016-04-16 10:34:50 -0300" value="138"/>
 <Record type="HKQuantityTypeIdentifierHeartRate" sourceName="Nicolas's Apple Watch" sourceVersion="2.2" device="&lt;&lt;HKDevice: 0x140c9ab20&gt;, name:Apple Watch, manufacturer:Apple, model:Watch, hardware:Watch1,2, software:2.2&gt;" unit="count/min" creationDate="2016-04-16 10:34:55 -0300" startDate="2016-04-16 10:34:55 -0300" endDate="2016-04-16 10:34:55 -0300" value="135"/>
 <Record type="HKQuantityTypeIdentifierHeartRate" sourceName="Nicolas's Apple Watch" sourceVersion="2.2" device="&lt;&lt;HKDevice: 0x140c9ad80&gt;, name:Apple Watch, manufacturer:Apple, model:Watch, hardware:Watch1,2, software:2.2&gt;" unit="count/min" creationDate="2016-04-16 10:35:00 -0300" startDate="2016-04-16 10:35:00 -0300" endDate="2016-04-16 10:35:00 -0300" value="137"/>
 <Record type="HKQuantityTypeIdentifierHeartRate" sourceName="Nicolas's Apple Watch" sourceVersion="2.2" device="&lt;&lt;HKDevice: 0x140c9afe0&gt;, name:Apple Watch, manufacturer:Apple, model:Watch, hardware:Watch1,2, software:2.2&gt;" unit="count/min" creationDate="2016-04-16 10:35:05 -0300" startDate="2016-04-16 10:35:05 -0300" endDate="2016-04-16 10:35:05 -0300" value="137"/>
 <Record type="HKQuantityTypeIdentifierHeartRate" sourceName="Nicolas's Apple Watch" sourceVersion="2.2" device="&lt;&lt;HKDevice: 0x140c9b240&gt;, name:Apple Watch, manufacturer:Apple, model:Watch, hardware:Watch1,2, software:2.2&gt;" unit="count/min" creationDate="2016-04-16 10:35:10 -0300" startDate="2016-04-16 10:35:10 -0300" endDate="2016-04-16 10:35:10 -0300" value="135"/>
 <Record type="HKQuantityTypeIdentifierHeartRate" sourceName="Nicolas's Apple Watch" sourceVersion="2.2" device="&lt;&lt;HKDevice: 0x140c9b4a0&gt;, name:Apple Watch, manufacturer:Apple, model:Watch, hardware:Watch1,2, software:2.2&gt;" unit="count/min" creationDate="2016-04-16 10:35:16 -0300" startDate="2016-04-16 10:35:15 -0300" endDate="2016-04-16 10:35:15 -0300" value="131"/>
 <Record type="HKQuantityTypeIdentifierHeartRate" sourceName="Nicolas's Apple Watch" sourceVersion="2.2" device="&lt;&lt;HKDevice: 0x140c9b700&gt;, name:Apple Watch, manufacturer:Apple, model:Watch, hardware:Watch1,2, software:2.2&gt;" unit="count/min" creationDate="2016-04-16 10:35:20 -0300" startDate="2016-04-16 10:35:20 -0300" endDate="2016-04-16 10:35:20 -0300" value="131"/>
 <Record type="HKQuantityTypeIdentifierHeartRate" sourceName="Nicolas's Apple Watch" sourceVersion="2.2" device="&lt;&lt;HKDevice: 0x140c9b960&gt;, name:Apple Watch, manufacturer:Apple, model:Watch, hardware:Watch1,2, software:2.2&gt;" unit="count/min" creationDate="2016-04-16 10:35:25 -0300" startDate="2016-04-16 10:35:25 -0300" endDate="2016-04-16 10:35:25 -0300" value="133"/>
 <Record type="HKQuantityTypeIdentifierHeartRate" sourceName="Nicolas's Apple Watch" sourceVersion="2.2" device="&lt;&lt;HKDevice: 0x140c9bbc0&gt;, name:Apple Watch, manufacturer:Apple, model:Watch, hardware:Watch1,2, software:2.2&gt;" unit="count/min" creationDate="2016-04-16 10:35:30 -0300" startDate="2016-04-16 10:35:30 -0300" endDate="2016-04-16 10:35:30 -0300" value="135"/>
 <Record type="HKQuantityTypeIdentifierHeartRate" sourceName="Nicolas's Apple Watch" sourceVersion="2.2" device="&lt;&lt;HKDevice: 0x140c9be20&gt;, name:Apple Watch, manufacturer:Apple, model:Watch, hardware:Watch1,2, software:2.2&gt;" unit="count/min" creationDate="2016-04-16 10:35:35 -0300" startDate="2016-04-16 10:35:35 -0300" endDate="2016-04-16 10:35:35 -0300" value="133"/>
 <Record type="HKQuantityTypeIdentifierHeartRate" sourceName="Nicolas's Apple Watch" sourceVersion="2.2" device="&lt;&lt;HKDevice: 0x140c9c080&gt;, name:Apple Watch, manufacturer:Apple, model:Watch, hardware:Watch1,2, software:2.2&gt;" unit="count/min" creationDate="2016-04-16 10:35:40 -0300" startDate="2016-04-16 10:35:40 -0300" endDate="2016-04-16 10:35:40 -0300" value="135"/>
 <Record type="HKQuantityTypeIdentifierHeartRate" sourceName="Nicolas's Apple Watch" sourceVersion="2.2" device="&lt;&lt;HKDevice: 0x140c9c2e0&gt;, name:Apple Watch, manufacturer:Apple, model:Watch, hardware:Watch1,2, software:2.2&gt;" unit="count/min" creationDate="2016-04-16 10:35:45 -0300" startDate="2016-04-16 10:35:45 -0300" endDate="2016-04-16 10:35:45 -0300" value="137"/>
 <Record type="HKQuantityTypeIdentifierHeartRate" sourceName="Nicolas's Apple Watch" sourceVersion="2.2" device="&lt;&lt;HKDevice: 0x140c9c540&gt;, name:Apple Watch, manufacturer:Apple, model:Watch, hardware:Watch1,2, software:2.2&gt;" unit="count/min" creationDate="2016-04-16 10:35:50 -0300" startDate="2016-04-16 10:35:50 -0300" endDate="2016-04-16 10:35:50 -0300" value="135"/>
 <Record type="HKQuantityTypeIdentifierHeartRate" sourceName="Nicolas's Apple Watch" sourceVersion="2.2" device="&lt;&lt;HKDevice: 0x140c9c7a0&gt;, name:Apple Watch, manufacturer:Apple, model:Watch, hardware:Watch1,2, software:2.2&gt;" unit="count/min" creationDate="2016-04-16 10:35:55 -0300" startDate="2016-04-16 10:35:55 -0300" endDate="2016-04-16 10:35:55 -0300" value="135"/>
 <Record type="HKQuantityTypeIdentifierHeartRate" sourceName="Nicolas's Apple Watch" sourceVersion="2.2" device="&lt;&lt;HKDevice: 0x140c9ca00&gt;, name:Apple Watch, manufacturer:Apple, model:Watch, hardware:Watch1,2, software:2.2&gt;" unit="count/min" creationDate="2016-04-16 10:36:00 -0300" startDate="2016-04-16 10:36:00 -0300" endDate="2016-04-16 10:36:00 -0300" value="135"/>
 <Record type="HKQuantityTypeIdentifierHeartRate" sourceName="Nicolas's Apple Watch" sourceVersion="2.2" device="&lt;&lt;HKDevice: 0x145b5ada0&gt;, name:Apple Watch, manufacturer:Apple, model:Watch, hardware:Watch1,2, software:2.2&gt;" unit="count/min" creationDate="2016-04-16 10:36:05 -0300" startDate="2016-04-16 10:36:05 -0300" endDate="2016-04-16 10:36:05 -0300" value="138"/>
 <Record type="HKQuantityTypeIdentifierHeartRate" sourceName="Nicolas's Apple Watch" sourceVersion="2.2" device="&lt;&lt;HKDevice: 0x145b5cce0&gt;, name:Apple Watch, manufacturer:Apple, model:Watch, hardware:Watch1,2, software:2.2&gt;" unit="count/min" creationDate="2016-04-16 10:36:10 -0300" startDate="2016-04-16 10:36:10 -0300" endDate="2016-04-16 10:36:10 -0300" value="137"/>
 <Record type="HKQuantityTypeIdentifierHeartRate" sourceName="Nicolas's Apple Watch" sourceVersion="2.2" device="&lt;&lt;HKDevice: 0x145b5cf40&gt;, name:Apple Watch, manufacturer:Apple, model:Watch, hardware:Watch1,2, software:2.2&gt;" unit="count/min" creationDate="2016-04-16 10:36:15 -0300" startDate="2016-04-16 10:36:15 -0300" endDate="2016-04-16 10:36:15 -0300" value="135"/>
 <Record type="HKQuantityTypeIdentifierHeartRate" sourceName="Nicolas's Apple Watch" sourceVersion="2.2" device="&lt;&lt;HKDevice: 0x145b5d1a0&gt;, name:Apple Watch, manufacturer:Apple, model:Watch, hardware:Watch1,2, software:2.2&gt;" unit="count/min" creationDate="2016-04-16 10:36:20 -0300" startDate="2016-04-16 10:36:20 -0300" endDate="2016-04-16 10:36:20 -0300" value="135"/>
 <Record type="HKQuantityTypeIdentifierHeartRate" sourceName="Nicolas's Apple Watch" sourceVersion="2.2" device="&lt;&lt;HKDevice: 0x145b5d400&gt;, name:Apple Watch, manufacturer:Apple, model:Watch, hardware:Watch1,2, software:2.2&gt;" unit="count/min" creationDate="2016-04-16 10:36:25 -0300" startDate="2016-04-16 10:36:25 -0300" endDate="2016-04-16 10:36:25 -0300" value="131"/>
 <Record type="HKQuantityTypeIdentifierHeartRate" sourceName="Nicolas's Apple Watch" sourceVersion="2.2" device="&lt;&lt;HKDevice: 0x145b5d660&gt;, name:Apple Watch, manufacturer:Apple, model:Watch, hardware:Watch1,2, software:2.2&gt;" unit="count/min" creationDate="2016-04-16 10:36:30 -0300" startDate="2016-04-16 10:36:30 -0300" endDate="2016-04-16 10:36:30 -0300" value="134"/>
 <Record type="HKQuantityTypeIdentifierHeartRate" sourceName="Nicolas's Apple Watch" sourceVersion="2.2" device="&lt;&lt;HKDevice: 0x145b5d8c0&gt;, name:Apple Watch, manufacturer:Apple, model:Watch, hardware:Watch1,2, software:2.2&gt;" unit="count/min" creationDate="2016-04-16 10:36:36 -0300" startDate="2016-04-16 10:36:35 -0300" endDate="2016-04-16 10:36:35 -0300" value="133"/>
 <Record type="HKQuantityTypeIdentifierHeartRate" sourceName="Nicolas's Apple Watch" sourceVersion="2.2" device="&lt;&lt;HKDevice: 0x145b5db20&gt;, name:Apple Watch, manufacturer:Apple, model:Watch, hardware:Watch1,2, software:2.2&gt;" unit="count/min" creationDate="2016-04-16 10:36:40 -0300" startDate="2016-04-16 10:36:40 -0300" endDate="2016-04-16 10:36:40 -0300" value="133"/>
 <Record type="HKQuantityTypeIdentifierHeartRate" sourceName="Nicolas's Apple Watch" sourceVersion="2.2" device="&lt;&lt;HKDevice: 0x145b5dd80&gt;, name:Apple Watch, manufacturer:Apple, model:Watch, hardware:Watch1,2, software:2.2&gt;" unit="count/min" creationDate="2016-04-16 10:36:45 -0300" startDate="2016-04-16 10:36:45 -0300" endDate="2016-04-16 10:36:45 -0300" value="133"/>
 <Record type="HKQuantityTypeIdentifierHeartRate" sourceName="Nicolas's Apple Watch" sourceVersion="2.2" device="&lt;&lt;HKDevice: 0x145b5dfe0&gt;, name:Apple Watch, manufacturer:Apple, model:Watch, hardware:Watch1,2, software:2.2&gt;" unit="count/min" creationDate="2016-04-16 10:36:50 -0300" startDate="2016-04-16 10:36:50 -0300" endDate="2016-04-16 10:36:50 -0300" value="131"/>
 <Record type="HKQuantityTypeIdentifierHeartRate" sourceName="Nicolas's Apple Watch" sourceVersion="2.2" device="&lt;&lt;HKDevice: 0x145b5e240&gt;, name:Apple Watch, manufacturer:Apple, model:Watch, hardware:Watch1,2, software:2.2&gt;" unit="count/min" creationDate="2016-04-16 10:36:55 -0300" startDate="2016-04-16 10:36:55 -0300" endDate="2016-04-16 10:36:55 -0300" value="132"/>
 <Record type="HKQuantityTypeIdentifierHeartRate" sourceName="Nicolas's Apple Watch" sourceVersion="2.2" device="&lt;&lt;HKDevice: 0x145b5e4a0&gt;, name:Apple Watch, manufacturer:Apple, model:Watch, hardware:Watch1,2, software:2.2&gt;" unit="count/min" creationDate="2016-04-16 10:37:00 -0300" startDate="2016-04-16 10:37:00 -0300" endDate="2016-04-16 10:37:00 -0300" value="133"/>
 <Record type="HKQuantityTypeIdentifierHeartRate" sourceName="Nicolas's Apple Watch" sourceVersion="2.2" device="&lt;&lt;HKDevice: 0x140c9cbb0&gt;, name:Apple Watch, manufacturer:Apple, model:Watch, hardware:Watch1,2, software:2.2&gt;" unit="count/min" creationDate="2016-04-16 10:37:05 -0300" startDate="2016-04-16 10:37:05 -0300" endDate="2016-04-16 10:37:05 -0300" value="134"/>
 <Record type="HKQuantityTypeIdentifierHeartRate" sourceName="Nicolas's Apple Watch" sourceVersion="2.2" device="&lt;&lt;HKDevice: 0x140c9cdf0&gt;, name:Apple Watch, manufacturer:Apple, model:Watch, hardware:Watch1,2, software:2.2&gt;" unit="count/min" creationDate="2016-04-16 10:37:10 -0300" startDate="2016-04-16 10:37:10 -0300" endDate="2016-04-16 10:37:10 -0300" value="133"/>
 <Record type="HKQuantityTypeIdentifierHeartRate" sourceName="Nicolas's Apple Watch" sourceVersion="2.2" device="&lt;&lt;HKDevice: 0x140c9d050&gt;, name:Apple Watch, manufacturer:Apple, model:Watch, hardware:Watch1,2, software:2.2&gt;" unit="count/min" creationDate="2016-04-16 10:37:15 -0300" startDate="2016-04-16 10:37:15 -0300" endDate="2016-04-16 10:37:15 -0300" value="134"/>
 <Record type="HKQuantityTypeIdentifierHeartRate" sourceName="Nicolas's Apple Watch" sourceVersion="2.2" device="&lt;&lt;HKDevice: 0x140c9d2b0&gt;, name:Apple Watch, manufacturer:Apple, model:Watch, hardware:Watch1,2, software:2.2&gt;" unit="count/min" creationDate="2016-04-16 10:37:20 -0300" startDate="2016-04-16 10:37:20 -0300" endDate="2016-04-16 10:37:20 -0300" value="133"/>
 <Record type="HKQuantityTypeIdentifierHeartRate" sourceName="Nicolas's Apple Watch" sourceVersion="2.2" device="&lt;&lt;HKDevice: 0x140c9d510&gt;, name:Apple Watch, manufacturer:Apple, model:Watch, hardware:Watch1,2, software:2.2&gt;" unit="count/min" creationDate="2016-04-16 10:37:25 -0300" startDate="2016-04-16 10:37:25 -0300" endDate="2016-04-16 10:37:25 -0300" value="133"/>
 <Record type="HKQuantityTypeIdentifierHeartRate" sourceName="Nicolas's Apple Watch" sourceVersion="2.2" device="&lt;&lt;HKDevice: 0x140c9d770&gt;, name:Apple Watch, manufacturer:Apple, model:Watch, hardware:Watch1,2, software:2.2&gt;" unit="count/min" creationDate="2016-04-16 10:37:30 -0300" startDate="2016-04-16 10:37:30 -0300" endDate="2016-04-16 10:37:30 -0300" value="134"/>
 <Record type="HKQuantityTypeIdentifierHeartRate" sourceName="Nicolas's Apple Watch" sourceVersion="2.2" device="&lt;&lt;HKDevice: 0x140c9d9d0&gt;, name:Apple Watch, manufacturer:Apple, model:Watch, hardware:Watch1,2, software:2.2&gt;" unit="count/min" creationDate="2016-04-16 10:37:35 -0300" startDate="2016-04-16 10:37:35 -0300" endDate="2016-04-16 10:37:35 -0300" value="131"/>
 <Record type="HKQuantityTypeIdentifierHeartRate" sourceName="Nicolas's Apple Watch" sourceVersion="2.2" device="&lt;&lt;HKDevice: 0x140c9dc30&gt;, name:Apple Watch, manufacturer:Apple, model:Watch, hardware:Watch1,2, software:2.2&gt;" unit="count/min" creationDate="2016-04-16 10:37:40 -0300" startDate="2016-04-16 10:37:40 -0300" endDate="2016-04-16 10:37:40 -0300" value="130"/>
 <Record type="HKQuantityTypeIdentifierHeartRate" sourceName="Nicolas's Apple Watch" sourceVersion="2.2" device="&lt;&lt;HKDevice: 0x140c9de90&gt;, name:Apple Watch, manufacturer:Apple, model:Watch, hardware:Watch1,2, software:2.2&gt;" unit="count/min" creationDate="2016-04-16 10:37:45 -0300" startDate="2016-04-16 10:37:45 -0300" endDate="2016-04-16 10:37:45 -0300" value="131"/>
 <Record type="HKQuantityTypeIdentifierHeartRate" sourceName="Nicolas's Apple Watch" sourceVersion="2.2" device="&lt;&lt;HKDevice: 0x140c9e0f0&gt;, name:Apple Watch, manufacturer:Apple, model:Watch, hardware:Watch1,2, software:2.2&gt;" unit="count/min" creationDate="2016-04-16 10:37:50 -0300" startDate="2016-04-16 10:37:50 -0300" endDate="2016-04-16 10:37:50 -0300" value="125"/>
 <Record type="HKQuantityTypeIdentifierHeartRate" sourceName="Nicolas's Apple Watch" sourceVersion="2.2" device="&lt;&lt;HKDevice: 0x140c9e350&gt;, name:Apple Watch, manufacturer:Apple, model:Watch, hardware:Watch1,2, software:2.2&gt;" unit="count/min" creationDate="2016-04-16 10:37:55 -0300" startDate="2016-04-16 10:37:55 -0300" endDate="2016-04-16 10:37:55 -0300" value="132"/>
 <Record type="HKQuantityTypeIdentifierHeartRate" sourceName="Nicolas's Apple Watch" sourceVersion="2.2" device="&lt;&lt;HKDevice: 0x140c9e5b0&gt;, name:Apple Watch, manufacturer:Apple, model:Watch, hardware:Watch1,2, software:2.2&gt;" unit="count/min" creationDate="2016-04-16 10:38:00 -0300" startDate="2016-04-16 10:38:00 -0300" endDate="2016-04-16 10:38:00 -0300" value="131"/>
 <Record type="HKQuantityTypeIdentifierHeartRate" sourceName="Nicolas's Apple Watch" sourceVersion="2.2" device="&lt;&lt;HKDevice: 0x140c9e810&gt;, name:Apple Watch, manufacturer:Apple, model:Watch, hardware:Watch1,2, software:2.2&gt;" unit="count/min" creationDate="2016-04-16 10:38:05 -0300" startDate="2016-04-16 10:38:05 -0300" endDate="2016-04-16 10:38:05 -0300" value="132"/>
 <Record type="HKQuantityTypeIdentifierHeartRate" sourceName="Nicolas's Apple Watch" sourceVersion="2.2" device="&lt;&lt;HKDevice: 0x140c9ea70&gt;, name:Apple Watch, manufacturer:Apple, model:Watch, hardware:Watch1,2, software:2.2&gt;" unit="count/min" creationDate="2016-04-16 10:38:10 -0300" startDate="2016-04-16 10:38:10 -0300" endDate="2016-04-16 10:38:10 -0300" value="133"/>
 <Record type="HKQuantityTypeIdentifierHeartRate" sourceName="Nicolas's Apple Watch" sourceVersion="2.2" device="&lt;&lt;HKDevice: 0x140c9ecd0&gt;, name:Apple Watch, manufacturer:Apple, model:Watch, hardware:Watch1,2, software:2.2&gt;" unit="count/min" creationDate="2016-04-16 10:38:15 -0300" startDate="2016-04-16 10:38:15 -0300" endDate="2016-04-16 10:38:15 -0300" value="132"/>
 <Record type="HKQuantityTypeIdentifierHeartRate" sourceName="Nicolas's Apple Watch" sourceVersion="2.2" device="&lt;&lt;HKDevice: 0x140c9ef30&gt;, name:Apple Watch, manufacturer:Apple, model:Watch, hardware:Watch1,2, software:2.2&gt;" unit="count/min" creationDate="2016-04-16 10:38:20 -0300" startDate="2016-04-16 10:38:20 -0300" endDate="2016-04-16 10:38:20 -0300" value="131"/>
 <Record type="HKQuantityTypeIdentifierHeartRate" sourceName="Nicolas's Apple Watch" sourceVersion="2.2" device="&lt;&lt;HKDevice: 0x140c9f190&gt;, name:Apple Watch, manufacturer:Apple, model:Watch, hardware:Watch1,2, software:2.2&gt;" unit="count/min" creationDate="2016-04-16 10:38:25 -0300" startDate="2016-04-16 10:38:25 -0300" endDate="2016-04-16 10:38:25 -0300" value="131"/>
 <Record type="HKQuantityTypeIdentifierHeartRate" sourceName="Nicolas's Apple Watch" sourceVersion="2.2" device="&lt;&lt;HKDevice: 0x140c9f3f0&gt;, name:Apple Watch, manufacturer:Apple, model:Watch, hardware:Watch1,2, software:2.2&gt;" unit="count/min" creationDate="2016-04-16 10:38:30 -0300" startDate="2016-04-16 10:38:30 -0300" endDate="2016-04-16 10:38:30 -0300" value="130"/>
 <Record type="HKQuantityTypeIdentifierHeartRate" sourceName="Nicolas's Apple Watch" sourceVersion="2.2" device="&lt;&lt;HKDevice: 0x140c9f650&gt;, name:Apple Watch, manufacturer:Apple, model:Watch, hardware:Watch1,2, software:2.2&gt;" unit="count/min" creationDate="2016-04-16 10:38:35 -0300" startDate="2016-04-16 10:38:35 -0300" endDate="2016-04-16 10:38:35 -0300" value="131"/>
 <Record type="HKQuantityTypeIdentifierHeartRate" sourceName="Nicolas's Apple Watch" sourceVersion="2.2" device="&lt;&lt;HKDevice: 0x140c9f8b0&gt;, name:Apple Watch, manufacturer:Apple, model:Watch, hardware:Watch1,2, software:2.2&gt;" unit="count/min" creationDate="2016-04-16 10:38:40 -0300" startDate="2016-04-16 10:38:40 -0300" endDate="2016-04-16 10:38:40 -0300" value="131"/>
 <Record type="HKQuantityTypeIdentifierHeartRate" sourceName="Nicolas's Apple Watch" sourceVersion="2.2" device="&lt;&lt;HKDevice: 0x140c9fb10&gt;, name:Apple Watch, manufacturer:Apple, model:Watch, hardware:Watch1,2, software:2.2&gt;" unit="count/min" creationDate="2016-04-16 10:38:45 -0300" startDate="2016-04-16 10:38:45 -0300" endDate="2016-04-16 10:38:45 -0300" value="131"/>
 <Record type="HKQuantityTypeIdentifierHeartRate" sourceName="Nicolas's Apple Watch" sourceVersion="2.2" device="&lt;&lt;HKDevice: 0x140c9fd70&gt;, name:Apple Watch, manufacturer:Apple, model:Watch, hardware:Watch1,2, software:2.2&gt;" unit="count/min" creationDate="2016-04-16 10:38:50 -0300" startDate="2016-04-16 10:38:50 -0300" endDate="2016-04-16 10:38:50 -0300" value="133"/>
 <Record type="HKQuantityTypeIdentifierHeartRate" sourceName="Nicolas's Apple Watch" sourceVersion="2.2" device="&lt;&lt;HKDevice: 0x140c9ffd0&gt;, name:Apple Watch, manufacturer:Apple, model:Watch, hardware:Watch1,2, software:2.2&gt;" unit="count/min" creationDate="2016-04-16 10:38:55 -0300" startDate="2016-04-16 10:38:55 -0300" endDate="2016-04-16 10:38:55 -0300" value="133"/>
 <Record type="HKQuantityTypeIdentifierHeartRate" sourceName="Nicolas's Apple Watch" sourceVersion="2.2" device="&lt;&lt;HKDevice: 0x140ca0230&gt;, name:Apple Watch, manufacturer:Apple, model:Watch, hardware:Watch1,2, software:2.2&gt;" unit="count/min" creationDate="2016-04-16 10:39:00 -0300" startDate="2016-04-16 10:39:00 -0300" endDate="2016-04-16 10:39:00 -0300" value="132"/>
 <Record type="HKQuantityTypeIdentifierHeartRate" sourceName="Nicolas's Apple Watch" sourceVersion="2.2" device="&lt;&lt;HKDevice: 0x140ca0490&gt;, name:Apple Watch, manufacturer:Apple, model:Watch, hardware:Watch1,2, software:2.2&gt;" unit="count/min" creationDate="2016-04-16 10:39:05 -0300" startDate="2016-04-16 10:39:05 -0300" endDate="2016-04-16 10:39:05 -0300" value="133"/>
 <Record type="HKQuantityTypeIdentifierHeartRate" sourceName="Nicolas's Apple Watch" sourceVersion="2.2" device="&lt;&lt;HKDevice: 0x145b5e7b0&gt;, name:Apple Watch, manufacturer:Apple, model:Watch, hardware:Watch1,2, software:2.2&gt;" unit="count/min" creationDate="2016-04-16 10:39:10 -0300" startDate="2016-04-16 10:39:10 -0300" endDate="2016-04-16 10:39:10 -0300" value="133"/>
 <Record type="HKQuantityTypeIdentifierHeartRate" sourceName="Nicolas's Apple Watch" sourceVersion="2.2" device="&lt;&lt;HKDevice: 0x145b5e9d0&gt;, name:Apple Watch, manufacturer:Apple, model:Watch, hardware:Watch1,2, software:2.2&gt;" unit="count/min" creationDate="2016-04-16 10:39:20 -0300" startDate="2016-04-16 10:39:20 -0300" endDate="2016-04-16 10:39:20 -0300" value="128"/>
 <Record type="HKQuantityTypeIdentifierHeartRate" sourceName="Nicolas's Apple Watch" sourceVersion="2.2" device="&lt;&lt;HKDevice: 0x145b5ec30&gt;, name:Apple Watch, manufacturer:Apple, model:Watch, hardware:Watch1,2, software:2.2&gt;" unit="count/min" creationDate="2016-04-16 10:39:25 -0300" startDate="2016-04-16 10:39:25 -0300" endDate="2016-04-16 10:39:25 -0300" value="134"/>
 <Record type="HKQuantityTypeIdentifierHeartRate" sourceName="Nicolas's Apple Watch" sourceVersion="2.2" device="&lt;&lt;HKDevice: 0x145b5ee90&gt;, name:Apple Watch, manufacturer:Apple, model:Watch, hardware:Watch1,2, software:2.2&gt;" unit="count/min" creationDate="2016-04-16 10:39:30 -0300" startDate="2016-04-16 10:39:30 -0300" endDate="2016-04-16 10:39:30 -0300" value="133"/>
 <Record type="HKQuantityTypeIdentifierHeartRate" sourceName="Nicolas's Apple Watch" sourceVersion="2.2" device="&lt;&lt;HKDevice: 0x145b5f0f0&gt;, name:Apple Watch, manufacturer:Apple, model:Watch, hardware:Watch1,2, software:2.2&gt;" unit="count/min" creationDate="2016-04-16 10:39:35 -0300" startDate="2016-04-16 10:39:35 -0300" endDate="2016-04-16 10:39:35 -0300" value="133"/>
 <Record type="HKQuantityTypeIdentifierHeartRate" sourceName="Nicolas's Apple Watch" sourceVersion="2.2" device="&lt;&lt;HKDevice: 0x145b5f350&gt;, name:Apple Watch, manufacturer:Apple, model:Watch, hardware:Watch1,2, software:2.2&gt;" unit="count/min" creationDate="2016-04-16 10:39:40 -0300" startDate="2016-04-16 10:39:40 -0300" endDate="2016-04-16 10:39:40 -0300" value="133"/>
 <Record type="HKQuantityTypeIdentifierHeartRate" sourceName="Nicolas's Apple Watch" sourceVersion="2.2" device="&lt;&lt;HKDevice: 0x145b5f5b0&gt;, name:Apple Watch, manufacturer:Apple, model:Watch, hardware:Watch1,2, software:2.2&gt;" unit="count/min" creationDate="2016-04-16 10:39:45 -0300" startDate="2016-04-16 10:39:45 -0300" endDate="2016-04-16 10:39:45 -0300" value="132"/>
 <Record type="HKQuantityTypeIdentifierHeartRate" sourceName="Nicolas's Apple Watch" sourceVersion="2.2" device="&lt;&lt;HKDevice: 0x145b5f810&gt;, name:Apple Watch, manufacturer:Apple, model:Watch, hardware:Watch1,2, software:2.2&gt;" unit="count/min" creationDate="2016-04-16 10:39:50 -0300" startDate="2016-04-16 10:39:50 -0300" endDate="2016-04-16 10:39:50 -0300" value="131"/>
 <Record type="HKQuantityTypeIdentifierHeartRate" sourceName="Nicolas's Apple Watch" sourceVersion="2.2" device="&lt;&lt;HKDevice: 0x145b5fa70&gt;, name:Apple Watch, manufacturer:Apple, model:Watch, hardware:Watch1,2, software:2.2&gt;" unit="count/min" creationDate="2016-04-16 10:39:55 -0300" startDate="2016-04-16 10:39:55 -0300" endDate="2016-04-16 10:39:55 -0300" value="131"/>
 <Record type="HKQuantityTypeIdentifierHeartRate" sourceName="Nicolas's Apple Watch" sourceVersion="2.2" device="&lt;&lt;HKDevice: 0x145b5fcd0&gt;, name:Apple Watch, manufacturer:Apple, model:Watch, hardware:Watch1,2, software:2.2&gt;" unit="count/min" creationDate="2016-04-16 10:40:00 -0300" startDate="2016-04-16 10:40:00 -0300" endDate="2016-04-16 10:40:00 -0300" value="126"/>
 <Record type="HKQuantityTypeIdentifierHeartRate" sourceName="Nicolas's Apple Watch" sourceVersion="2.2" device="&lt;&lt;HKDevice: 0x145b5ff30&gt;, name:Apple Watch, manufacturer:Apple, model:Watch, hardware:Watch1,2, software:2.2&gt;" unit="count/min" creationDate="2016-04-16 10:40:05 -0300" startDate="2016-04-16 10:40:05 -0300" endDate="2016-04-16 10:40:05 -0300" value="127"/>
 <Record type="HKQuantityTypeIdentifierHeartRate" sourceName="Nicolas's Apple Watch" sourceVersion="2.2" device="&lt;&lt;HKDevice: 0x145b60190&gt;, name:Apple Watch, manufacturer:Apple, model:Watch, hardware:Watch1,2, software:2.2&gt;" unit="count/min" creationDate="2016-04-16 10:40:10 -0300" startDate="2016-04-16 10:40:10 -0300" endDate="2016-04-16 10:40:10 -0300" value="124"/>
 <Record type="HKQuantityTypeIdentifierHeartRate" sourceName="Nicolas's Apple Watch" sourceVersion="2.2" device="&lt;&lt;HKDevice: 0x145b603f0&gt;, name:Apple Watch, manufacturer:Apple, model:Watch, hardware:Watch1,2, software:2.2&gt;" unit="count/min" creationDate="2016-04-16 10:40:15 -0300" startDate="2016-04-16 10:40:15 -0300" endDate="2016-04-16 10:40:15 -0300" value="125"/>
 <Record type="HKQuantityTypeIdentifierHeartRate" sourceName="Nicolas's Apple Watch" sourceVersion="2.2" device="&lt;&lt;HKDevice: 0x145b60650&gt;, name:Apple Watch, manufacturer:Apple, model:Watch, hardware:Watch1,2, software:2.2&gt;" unit="count/min" creationDate="2016-04-16 10:40:20 -0300" startDate="2016-04-16 10:40:20 -0300" endDate="2016-04-16 10:40:20 -0300" value="127"/>
 <Record type="HKQuantityTypeIdentifierHeartRate" sourceName="Nicolas's Apple Watch" sourceVersion="2.2" device="&lt;&lt;HKDevice: 0x145b608b0&gt;, name:Apple Watch, manufacturer:Apple, model:Watch, hardware:Watch1,2, software:2.2&gt;" unit="count/min" creationDate="2016-04-16 10:40:25 -0300" startDate="2016-04-16 10:40:25 -0300" endDate="2016-04-16 10:40:25 -0300" value="125"/>
 <Record type="HKQuantityTypeIdentifierHeartRate" sourceName="Nicolas's Apple Watch" sourceVersion="2.2" device="&lt;&lt;HKDevice: 0x145b60b10&gt;, name:Apple Watch, manufacturer:Apple, model:Watch, hardware:Watch1,2, software:2.2&gt;" unit="count/min" creationDate="2016-04-16 10:40:30 -0300" startDate="2016-04-16 10:40:30 -0300" endDate="2016-04-16 10:40:30 -0300" value="130"/>
 <Record type="HKQuantityTypeIdentifierHeartRate" sourceName="Nicolas's Apple Watch" sourceVersion="2.2" device="&lt;&lt;HKDevice: 0x145b60d70&gt;, name:Apple Watch, manufacturer:Apple, model:Watch, hardware:Watch1,2, software:2.2&gt;" unit="count/min" creationDate="2016-04-16 10:40:35 -0300" startDate="2016-04-16 10:40:35 -0300" endDate="2016-04-16 10:40:35 -0300" value="128"/>
 <Record type="HKQuantityTypeIdentifierHeartRate" sourceName="Nicolas's Apple Watch" sourceVersion="2.2" device="&lt;&lt;HKDevice: 0x145b60fd0&gt;, name:Apple Watch, manufacturer:Apple, model:Watch, hardware:Watch1,2, software:2.2&gt;" unit="count/min" creationDate="2016-04-16 10:40:40 -0300" startDate="2016-04-16 10:40:40 -0300" endDate="2016-04-16 10:40:40 -0300" value="130"/>
 <Record type="HKQuantityTypeIdentifierHeartRate" sourceName="Nicolas's Apple Watch" sourceVersion="2.2" device="&lt;&lt;HKDevice: 0x145b61230&gt;, name:Apple Watch, manufacturer:Apple, model:Watch, hardware:Watch1,2, software:2.2&gt;" unit="count/min" creationDate="2016-04-16 10:40:45 -0300" startDate="2016-04-16 10:40:45 -0300" endDate="2016-04-16 10:40:45 -0300" value="131"/>
 <Record type="HKQuantityTypeIdentifierHeartRate" sourceName="Nicolas's Apple Watch" sourceVersion="2.2" device="&lt;&lt;HKDevice: 0x145b61490&gt;, name:Apple Watch, manufacturer:Apple, model:Watch, hardware:Watch1,2, software:2.2&gt;" unit="count/min" creationDate="2016-04-16 10:40:50 -0300" startDate="2016-04-16 10:40:50 -0300" endDate="2016-04-16 10:40:50 -0300" value="130"/>
 <Record type="HKQuantityTypeIdentifierHeartRate" sourceName="Nicolas's Apple Watch" sourceVersion="2.2" device="&lt;&lt;HKDevice: 0x145b616f0&gt;, name:Apple Watch, manufacturer:Apple, model:Watch, hardware:Watch1,2, software:2.2&gt;" unit="count/min" creationDate="2016-04-16 10:40:55 -0300" startDate="2016-04-16 10:40:55 -0300" endDate="2016-04-16 10:40:55 -0300" value="130"/>
 <Record type="HKQuantityTypeIdentifierHeartRate" sourceName="Nicolas's Apple Watch" sourceVersion="2.2" device="&lt;&lt;HKDevice: 0x145b61950&gt;, name:Apple Watch, manufacturer:Apple, model:Watch, hardware:Watch1,2, software:2.2&gt;" unit="count/min" creationDate="2016-04-16 10:41:00 -0300" startDate="2016-04-16 10:41:00 -0300" endDate="2016-04-16 10:41:00 -0300" value="130"/>
 <Record type="HKQuantityTypeIdentifierHeartRate" sourceName="Nicolas's Apple Watch" sourceVersion="2.2" device="&lt;&lt;HKDevice: 0x145b61bb0&gt;, name:Apple Watch, manufacturer:Apple, model:Watch, hardware:Watch1,2, software:2.2&gt;" unit="count/min" creationDate="2016-04-16 10:41:05 -0300" startDate="2016-04-16 10:41:05 -0300" endDate="2016-04-16 10:41:05 -0300" value="124"/>
 <Record type="HKQuantityTypeIdentifierHeartRate" sourceName="Nicolas's Apple Watch" sourceVersion="2.2" device="&lt;&lt;HKDevice: 0x145b61e10&gt;, name:Apple Watch, manufacturer:Apple, model:Watch, hardware:Watch1,2, software:2.2&gt;" unit="count/min" creationDate="2016-04-16 10:41:10 -0300" startDate="2016-04-16 10:41:10 -0300" endDate="2016-04-16 10:41:10 -0300" value="126"/>
 <Record type="HKQuantityTypeIdentifierHeartRate" sourceName="Nicolas's Apple Watch" sourceVersion="2.2" device="&lt;&lt;HKDevice: 0x145b62070&gt;, name:Apple Watch, manufacturer:Apple, model:Watch, hardware:Watch1,2, software:2.2&gt;" unit="count/min" creationDate="2016-04-16 10:41:15 -0300" startDate="2016-04-16 10:41:15 -0300" endDate="2016-04-16 10:41:15 -0300" value="131"/>
 <Record type="HKQuantityTypeIdentifierHeartRate" sourceName="Nicolas's Apple Watch" sourceVersion="2.2" device="&lt;&lt;HKDevice: 0x140ca0630&gt;, name:Apple Watch, manufacturer:Apple, model:Watch, hardware:Watch1,2, software:2.2&gt;" unit="count/min" creationDate="2016-04-16 10:41:20 -0300" startDate="2016-04-16 10:41:20 -0300" endDate="2016-04-16 10:41:20 -0300" value="130"/>
 <Record type="HKQuantityTypeIdentifierHeartRate" sourceName="Nicolas's Apple Watch" sourceVersion="2.2" device="&lt;&lt;HKDevice: 0x140ca0870&gt;, name:Apple Watch, manufacturer:Apple, model:Watch, hardware:Watch1,2, software:2.2&gt;" unit="count/min" creationDate="2016-04-16 10:41:25 -0300" startDate="2016-04-16 10:41:25 -0300" endDate="2016-04-16 10:41:25 -0300" value="132"/>
 <Record type="HKQuantityTypeIdentifierHeartRate" sourceName="Nicolas's Apple Watch" sourceVersion="2.2" device="&lt;&lt;HKDevice: 0x140ca0ad0&gt;, name:Apple Watch, manufacturer:Apple, model:Watch, hardware:Watch1,2, software:2.2&gt;" unit="count/min" creationDate="2016-04-16 10:41:30 -0300" startDate="2016-04-16 10:41:30 -0300" endDate="2016-04-16 10:41:30 -0300" value="132"/>
 <Record type="HKQuantityTypeIdentifierHeartRate" sourceName="Nicolas's Apple Watch" sourceVersion="2.2" device="&lt;&lt;HKDevice: 0x140ca0d30&gt;, name:Apple Watch, manufacturer:Apple, model:Watch, hardware:Watch1,2, software:2.2&gt;" unit="count/min" creationDate="2016-04-16 10:41:35 -0300" startDate="2016-04-16 10:41:35 -0300" endDate="2016-04-16 10:41:35 -0300" value="132"/>
 <Record type="HKQuantityTypeIdentifierHeartRate" sourceName="Nicolas's Apple Watch" sourceVersion="2.2" device="&lt;&lt;HKDevice: 0x140ca0f90&gt;, name:Apple Watch, manufacturer:Apple, model:Watch, hardware:Watch1,2, software:2.2&gt;" unit="count/min" creationDate="2016-04-16 10:41:40 -0300" startDate="2016-04-16 10:41:40 -0300" endDate="2016-04-16 10:41:40 -0300" value="132"/>
 <Record type="HKQuantityTypeIdentifierHeartRate" sourceName="Nicolas's Apple Watch" sourceVersion="2.2" device="&lt;&lt;HKDevice: 0x140ca11f0&gt;, name:Apple Watch, manufacturer:Apple, model:Watch, hardware:Watch1,2, software:2.2&gt;" unit="count/min" creationDate="2016-04-16 10:41:45 -0300" startDate="2016-04-16 10:41:45 -0300" endDate="2016-04-16 10:41:45 -0300" value="132"/>
 <Record type="HKQuantityTypeIdentifierHeartRate" sourceName="Nicolas's Apple Watch" sourceVersion="2.2" device="&lt;&lt;HKDevice: 0x140ca1450&gt;, name:Apple Watch, manufacturer:Apple, model:Watch, hardware:Watch1,2, software:2.2&gt;" unit="count/min" creationDate="2016-04-16 10:41:50 -0300" startDate="2016-04-16 10:41:50 -0300" endDate="2016-04-16 10:41:50 -0300" value="132"/>
 <Record type="HKQuantityTypeIdentifierHeartRate" sourceName="Nicolas's Apple Watch" sourceVersion="2.2" device="&lt;&lt;HKDevice: 0x140ca16b0&gt;, name:Apple Watch, manufacturer:Apple, model:Watch, hardware:Watch1,2, software:2.2&gt;" unit="count/min" creationDate="2016-04-16 10:41:55 -0300" startDate="2016-04-16 10:41:55 -0300" endDate="2016-04-16 10:41:55 -0300" value="131"/>
 <Record type="HKQuantityTypeIdentifierHeartRate" sourceName="Nicolas's Apple Watch" sourceVersion="2.2" device="&lt;&lt;HKDevice: 0x140ca1910&gt;, name:Apple Watch, manufacturer:Apple, model:Watch, hardware:Watch1,2, software:2.2&gt;" unit="count/min" creationDate="2016-04-16 10:42:00 -0300" startDate="2016-04-16 10:42:00 -0300" endDate="2016-04-16 10:42:00 -0300" value="127"/>
 <Record type="HKQuantityTypeIdentifierHeartRate" sourceName="Nicolas's Apple Watch" sourceVersion="2.2" device="&lt;&lt;HKDevice: 0x140ca1b70&gt;, name:Apple Watch, manufacturer:Apple, model:Watch, hardware:Watch1,2, software:2.2&gt;" unit="count/min" creationDate="2016-04-16 10:42:05 -0300" startDate="2016-04-16 10:42:05 -0300" endDate="2016-04-16 10:42:05 -0300" value="128"/>
 <Record type="HKQuantityTypeIdentifierHeartRate" sourceName="Nicolas's Apple Watch" sourceVersion="2.2" device="&lt;&lt;HKDevice: 0x140ca1dd0&gt;, name:Apple Watch, manufacturer:Apple, model:Watch, hardware:Watch1,2, software:2.2&gt;" unit="count/min" creationDate="2016-04-16 10:42:10 -0300" startDate="2016-04-16 10:42:10 -0300" endDate="2016-04-16 10:42:10 -0300" value="129"/>
 <Record type="HKQuantityTypeIdentifierHeartRate" sourceName="Nicolas's Apple Watch" sourceVersion="2.2" device="&lt;&lt;HKDevice: 0x140ca2030&gt;, name:Apple Watch, manufacturer:Apple, model:Watch, hardware:Watch1,2, software:2.2&gt;" unit="count/min" creationDate="2016-04-16 10:42:15 -0300" startDate="2016-04-16 10:42:15 -0300" endDate="2016-04-16 10:42:15 -0300" value="129"/>
 <Record type="HKQuantityTypeIdentifierHeartRate" sourceName="Nicolas's Apple Watch" sourceVersion="2.2" device="&lt;&lt;HKDevice: 0x140ca2290&gt;, name:Apple Watch, manufacturer:Apple, model:Watch, hardware:Watch1,2, software:2.2&gt;" unit="count/min" creationDate="2016-04-16 10:42:20 -0300" startDate="2016-04-16 10:42:20 -0300" endDate="2016-04-16 10:42:20 -0300" value="129"/>
 <Record type="HKQuantityTypeIdentifierHeartRate" sourceName="Nicolas's Apple Watch" sourceVersion="2.2" device="&lt;&lt;HKDevice: 0x145b62320&gt;, name:Apple Watch, manufacturer:Apple, model:Watch, hardware:Watch1,2, software:2.2&gt;" unit="count/min" creationDate="2016-04-16 10:42:25 -0300" startDate="2016-04-16 10:42:25 -0300" endDate="2016-04-16 10:42:25 -0300" value="129"/>
 <Record type="HKQuantityTypeIdentifierHeartRate" sourceName="Nicolas's Apple Watch" sourceVersion="2.2" device="&lt;&lt;HKDevice: 0x145b62580&gt;, name:Apple Watch, manufacturer:Apple, model:Watch, hardware:Watch1,2, software:2.2&gt;" unit="count/min" creationDate="2016-04-16 10:42:30 -0300" startDate="2016-04-16 10:42:30 -0300" endDate="2016-04-16 10:42:30 -0300" value="129"/>
 <Record type="HKQuantityTypeIdentifierHeartRate" sourceName="Nicolas's Apple Watch" sourceVersion="2.2" device="&lt;&lt;HKDevice: 0x145b627e0&gt;, name:Apple Watch, manufacturer:Apple, model:Watch, hardware:Watch1,2, software:2.2&gt;" unit="count/min" creationDate="2016-04-16 10:42:35 -0300" startDate="2016-04-16 10:42:35 -0300" endDate="2016-04-16 10:42:35 -0300" value="129"/>
 <Record type="HKQuantityTypeIdentifierHeartRate" sourceName="Nicolas's Apple Watch" sourceVersion="2.2" device="&lt;&lt;HKDevice: 0x145b62a40&gt;, name:Apple Watch, manufacturer:Apple, model:Watch, hardware:Watch1,2, software:2.2&gt;" unit="count/min" creationDate="2016-04-16 10:42:40 -0300" startDate="2016-04-16 10:42:40 -0300" endDate="2016-04-16 10:42:40 -0300" value="129"/>
 <Record type="HKQuantityTypeIdentifierHeartRate" sourceName="Nicolas's Apple Watch" sourceVersion="2.2" device="&lt;&lt;HKDevice: 0x145b62ca0&gt;, name:Apple Watch, manufacturer:Apple, model:Watch, hardware:Watch1,2, software:2.2&gt;" unit="count/min" creationDate="2016-04-16 10:42:45 -0300" startDate="2016-04-16 10:42:45 -0300" endDate="2016-04-16 10:42:45 -0300" value="129"/>
 <Record type="HKQuantityTypeIdentifierHeartRate" sourceName="Nicolas's Apple Watch" sourceVersion="2.2" device="&lt;&lt;HKDevice: 0x145b62f00&gt;, name:Apple Watch, manufacturer:Apple, model:Watch, hardware:Watch1,2, software:2.2&gt;" unit="count/min" creationDate="2016-04-16 10:42:50 -0300" startDate="2016-04-16 10:42:50 -0300" endDate="2016-04-16 10:42:50 -0300" value="137"/>
 <Record type="HKQuantityTypeIdentifierHeartRate" sourceName="Nicolas's Apple Watch" sourceVersion="2.2" device="&lt;&lt;HKDevice: 0x145b63160&gt;, name:Apple Watch, manufacturer:Apple, model:Watch, hardware:Watch1,2, software:2.2&gt;" unit="count/min" creationDate="2016-04-16 10:42:55 -0300" startDate="2016-04-16 10:42:55 -0300" endDate="2016-04-16 10:42:55 -0300" value="135"/>
 <Record type="HKQuantityTypeIdentifierHeartRate" sourceName="Nicolas's Apple Watch" sourceVersion="2.2" device="&lt;&lt;HKDevice: 0x145b633c0&gt;, name:Apple Watch, manufacturer:Apple, model:Watch, hardware:Watch1,2, software:2.2&gt;" unit="count/min" creationDate="2016-04-16 10:43:00 -0300" startDate="2016-04-16 10:43:00 -0300" endDate="2016-04-16 10:43:00 -0300" value="131"/>
 <Record type="HKQuantityTypeIdentifierHeartRate" sourceName="Nicolas's Apple Watch" sourceVersion="2.2" device="&lt;&lt;HKDevice: 0x145b63620&gt;, name:Apple Watch, manufacturer:Apple, model:Watch, hardware:Watch1,2, software:2.2&gt;" unit="count/min" creationDate="2016-04-16 10:43:05 -0300" startDate="2016-04-16 10:43:05 -0300" endDate="2016-04-16 10:43:05 -0300" value="133"/>
 <Record type="HKQuantityTypeIdentifierHeartRate" sourceName="Nicolas's Apple Watch" sourceVersion="2.2" device="&lt;&lt;HKDevice: 0x145b63880&gt;, name:Apple Watch, manufacturer:Apple, model:Watch, hardware:Watch1,2, software:2.2&gt;" unit="count/min" creationDate="2016-04-16 10:43:10 -0300" startDate="2016-04-16 10:43:10 -0300" endDate="2016-04-16 10:43:10 -0300" value="133"/>
 <Record type="HKQuantityTypeIdentifierHeartRate" sourceName="Nicolas's Apple Watch" sourceVersion="2.2" device="&lt;&lt;HKDevice: 0x145b63ae0&gt;, name:Apple Watch, manufacturer:Apple, model:Watch, hardware:Watch1,2, software:2.2&gt;" unit="count/min" creationDate="2016-04-16 10:43:15 -0300" startDate="2016-04-16 10:43:15 -0300" endDate="2016-04-16 10:43:15 -0300" value="127"/>
 <Record type="HKQuantityTypeIdentifierHeartRate" sourceName="Nicolas's Apple Watch" sourceVersion="2.2" device="&lt;&lt;HKDevice: 0x140ca24f0&gt;, name:Apple Watch, manufacturer:Apple, model:Watch, hardware:Watch1,2, software:2.2&gt;" unit="count/min" creationDate="2016-04-16 10:43:20 -0300" startDate="2016-04-16 10:43:20 -0300" endDate="2016-04-16 10:43:20 -0300" value="129"/>
 <Record type="HKQuantityTypeIdentifierHeartRate" sourceName="Nicolas's Apple Watch" sourceVersion="2.2" device="&lt;&lt;HKDevice: 0x140ca2750&gt;, name:Apple Watch, manufacturer:Apple, model:Watch, hardware:Watch1,2, software:2.2&gt;" unit="count/min" creationDate="2016-04-16 10:43:25 -0300" startDate="2016-04-16 10:43:25 -0300" endDate="2016-04-16 10:43:25 -0300" value="130"/>
 <Record type="HKQuantityTypeIdentifierHeartRate" sourceName="Nicolas's Apple Watch" sourceVersion="2.2" device="&lt;&lt;HKDevice: 0x140ca29b0&gt;, name:Apple Watch, manufacturer:Apple, model:Watch, hardware:Watch1,2, software:2.2&gt;" unit="count/min" creationDate="2016-04-16 10:43:30 -0300" startDate="2016-04-16 10:43:30 -0300" endDate="2016-04-16 10:43:30 -0300" value="130"/>
 <Record type="HKQuantityTypeIdentifierHeartRate" sourceName="Nicolas's Apple Watch" sourceVersion="2.2" device="&lt;&lt;HKDevice: 0x140ca2c10&gt;, name:Apple Watch, manufacturer:Apple, model:Watch, hardware:Watch1,2, software:2.2&gt;" unit="count/min" creationDate="2016-04-16 10:43:35 -0300" startDate="2016-04-16 10:43:35 -0300" endDate="2016-04-16 10:43:35 -0300" value="126"/>
 <Record type="HKQuantityTypeIdentifierHeartRate" sourceName="Nicolas's Apple Watch" sourceVersion="2.2" device="&lt;&lt;HKDevice: 0x140ca2e70&gt;, name:Apple Watch, manufacturer:Apple, model:Watch, hardware:Watch1,2, software:2.2&gt;" unit="count/min" creationDate="2016-04-16 10:43:40 -0300" startDate="2016-04-16 10:43:40 -0300" endDate="2016-04-16 10:43:40 -0300" value="129"/>
 <Record type="HKQuantityTypeIdentifierHeartRate" sourceName="Nicolas's Apple Watch" sourceVersion="2.2" device="&lt;&lt;HKDevice: 0x140ca30d0&gt;, name:Apple Watch, manufacturer:Apple, model:Watch, hardware:Watch1,2, software:2.2&gt;" unit="count/min" creationDate="2016-04-16 10:43:45 -0300" startDate="2016-04-16 10:43:45 -0300" endDate="2016-04-16 10:43:45 -0300" value="128"/>
 <Record type="HKQuantityTypeIdentifierHeartRate" sourceName="Nicolas's Apple Watch" sourceVersion="2.2" device="&lt;&lt;HKDevice: 0x140ca3330&gt;, name:Apple Watch, manufacturer:Apple, model:Watch, hardware:Watch1,2, software:2.2&gt;" unit="count/min" creationDate="2016-04-16 10:43:50 -0300" startDate="2016-04-16 10:43:50 -0300" endDate="2016-04-16 10:43:50 -0300" value="126"/>
 <Record type="HKQuantityTypeIdentifierHeartRate" sourceName="Nicolas's Apple Watch" sourceVersion="2.2" device="&lt;&lt;HKDevice: 0x140ca3590&gt;, name:Apple Watch, manufacturer:Apple, model:Watch, hardware:Watch1,2, software:2.2&gt;" unit="count/min" creationDate="2016-04-16 10:43:55 -0300" startDate="2016-04-16 10:43:55 -0300" endDate="2016-04-16 10:43:55 -0300" value="128"/>
 <Record type="HKQuantityTypeIdentifierHeartRate" sourceName="Nicolas's Apple Watch" sourceVersion="2.2" device="&lt;&lt;HKDevice: 0x140ca37f0&gt;, name:Apple Watch, manufacturer:Apple, model:Watch, hardware:Watch1,2, software:2.2&gt;" unit="count/min" creationDate="2016-04-16 10:44:00 -0300" startDate="2016-04-16 10:44:00 -0300" endDate="2016-04-16 10:44:00 -0300" value="127"/>
 <Record type="HKQuantityTypeIdentifierHeartRate" sourceName="Nicolas's Apple Watch" sourceVersion="2.2" device="&lt;&lt;HKDevice: 0x140ca3a50&gt;, name:Apple Watch, manufacturer:Apple, model:Watch, hardware:Watch1,2, software:2.2&gt;" unit="count/min" creationDate="2016-04-16 10:44:05 -0300" startDate="2016-04-16 10:44:05 -0300" endDate="2016-04-16 10:44:05 -0300" value="127"/>
 <Record type="HKQuantityTypeIdentifierHeartRate" sourceName="Nicolas's Apple Watch" sourceVersion="2.2" device="&lt;&lt;HKDevice: 0x145b63e80&gt;, name:Apple Watch, manufacturer:Apple, model:Watch, hardware:Watch1,2, software:2.2&gt;" unit="count/min" creationDate="2016-04-16 10:44:10 -0300" startDate="2016-04-16 10:44:10 -0300" endDate="2016-04-16 10:44:10 -0300" value="126"/>
 <Record type="HKQuantityTypeIdentifierHeartRate" sourceName="Nicolas's Apple Watch" sourceVersion="2.2" device="&lt;&lt;HKDevice: 0x145b640e0&gt;, name:Apple Watch, manufacturer:Apple, model:Watch, hardware:Watch1,2, software:2.2&gt;" unit="count/min" creationDate="2016-04-16 10:44:20 -0300" startDate="2016-04-16 10:44:20 -0300" endDate="2016-04-16 10:44:20 -0300" value="126"/>
 <Record type="HKQuantityTypeIdentifierHeartRate" sourceName="Nicolas's Apple Watch" sourceVersion="2.2" device="&lt;&lt;HKDevice: 0x145b64340&gt;, name:Apple Watch, manufacturer:Apple, model:Watch, hardware:Watch1,2, software:2.2&gt;" unit="count/min" creationDate="2016-04-16 10:44:25 -0300" startDate="2016-04-16 10:44:25 -0300" endDate="2016-04-16 10:44:25 -0300" value="125"/>
 <Record type="HKQuantityTypeIdentifierHeartRate" sourceName="Nicolas's Apple Watch" sourceVersion="2.2" device="&lt;&lt;HKDevice: 0x145b645a0&gt;, name:Apple Watch, manufacturer:Apple, model:Watch, hardware:Watch1,2, software:2.2&gt;" unit="count/min" creationDate="2016-04-16 10:44:30 -0300" startDate="2016-04-16 10:44:30 -0300" endDate="2016-04-16 10:44:30 -0300" value="113"/>
 <Record type="HKQuantityTypeIdentifierHeartRate" sourceName="Nicolas's Apple Watch" sourceVersion="2.2" device="&lt;&lt;HKDevice: 0x145b64800&gt;, name:Apple Watch, manufacturer:Apple, model:Watch, hardware:Watch1,2, software:2.2&gt;" unit="count/min" creationDate="2016-04-16 10:44:35 -0300" startDate="2016-04-16 10:44:35 -0300" endDate="2016-04-16 10:44:35 -0300" value="113"/>
 <Record type="HKQuantityTypeIdentifierHeartRate" sourceName="Nicolas's Apple Watch" sourceVersion="2.2" device="&lt;&lt;HKDevice: 0x145b64a60&gt;, name:Apple Watch, manufacturer:Apple, model:Watch, hardware:Watch1,2, software:2.2&gt;" unit="count/min" creationDate="2016-04-16 10:44:40 -0300" startDate="2016-04-16 10:44:40 -0300" endDate="2016-04-16 10:44:40 -0300" value="113"/>
 <Record type="HKQuantityTypeIdentifierHeartRate" sourceName="Nicolas's Apple Watch" sourceVersion="2.2" device="&lt;&lt;HKDevice: 0x145b64cc0&gt;, name:Apple Watch, manufacturer:Apple, model:Watch, hardware:Watch1,2, software:2.2&gt;" unit="count/min" creationDate="2016-04-16 10:44:46 -0300" startDate="2016-04-16 10:44:45 -0300" endDate="2016-04-16 10:44:45 -0300" value="113"/>
 <Record type="HKQuantityTypeIdentifierHeartRate" sourceName="Nicolas's Apple Watch" sourceVersion="2.2" device="&lt;&lt;HKDevice: 0x145b64f20&gt;, name:Apple Watch, manufacturer:Apple, model:Watch, hardware:Watch1,2, software:2.2&gt;" unit="count/min" creationDate="2016-04-16 10:46:35 -0300" startDate="2016-04-16 10:46:35 -0300" endDate="2016-04-16 10:46:35 -0300" value="59"/>
 <Record type="HKQuantityTypeIdentifierHeartRate" sourceName="Nicolas's Apple Watch" sourceVersion="2.2" device="&lt;&lt;HKDevice: 0x145b65180&gt;, name:Apple Watch, manufacturer:Apple, model:Watch, hardware:Watch1,2, software:2.2&gt;" unit="count/min" creationDate="2016-04-16 10:46:40 -0300" startDate="2016-04-16 10:46:40 -0300" endDate="2016-04-16 10:46:40 -0300" value="59"/>
 <Record type="HKQuantityTypeIdentifierHeartRate" sourceName="Nicolas's Apple Watch" sourceVersion="2.2" device="&lt;&lt;HKDevice: 0x145b653e0&gt;, name:Apple Watch, manufacturer:Apple, model:Watch, hardware:Watch1,2, software:2.2&gt;" unit="count/min" creationDate="2016-04-16 10:46:45 -0300" startDate="2016-04-16 10:46:45 -0300" endDate="2016-04-16 10:46:45 -0300" value="58"/>
 <Record type="HKQuantityTypeIdentifierHeartRate" sourceName="Nicolas's Apple Watch" sourceVersion="2.2" device="&lt;&lt;HKDevice: 0x145b65640&gt;, name:Apple Watch, manufacturer:Apple, model:Watch, hardware:Watch1,2, software:2.2&gt;" unit="count/min" creationDate="2016-04-16 10:46:50 -0300" startDate="2016-04-16 10:46:50 -0300" endDate="2016-04-16 10:46:50 -0300" value="58"/>
 <Record type="HKQuantityTypeIdentifierHeartRate" sourceName="Nicolas's Apple Watch" sourceVersion="2.2" device="&lt;&lt;HKDevice: 0x145b658a0&gt;, name:Apple Watch, manufacturer:Apple, model:Watch, hardware:Watch1,2, software:2.2&gt;" unit="count/min" creationDate="2016-04-16 10:46:55 -0300" startDate="2016-04-16 10:46:55 -0300" endDate="2016-04-16 10:46:55 -0300" value="58"/>
 <Record type="HKQuantityTypeIdentifierHeartRate" sourceName="Nicolas's Apple Watch" sourceVersion="2.2" device="&lt;&lt;HKDevice: 0x145b65b00&gt;, name:Apple Watch, manufacturer:Apple, model:Watch, hardware:Watch1,2, software:2.2&gt;" unit="count/min" creationDate="2016-04-16 10:47:00 -0300" startDate="2016-04-16 10:47:00 -0300" endDate="2016-04-16 10:47:00 -0300" value="58"/>
 <Record type="HKQuantityTypeIdentifierHeartRate" sourceName="Nicolas's Apple Watch" sourceVersion="2.2" device="&lt;&lt;HKDevice: 0x145b65d60&gt;, name:Apple Watch, manufacturer:Apple, model:Watch, hardware:Watch1,2, software:2.2&gt;" unit="count/min" creationDate="2016-04-16 10:47:05 -0300" startDate="2016-04-16 10:47:05 -0300" endDate="2016-04-16 10:47:05 -0300" value="58"/>
 <Record type="HKQuantityTypeIdentifierHeartRate" sourceName="Nicolas's Apple Watch" sourceVersion="2.2" device="&lt;&lt;HKDevice: 0x145b65fc0&gt;, name:Apple Watch, manufacturer:Apple, model:Watch, hardware:Watch1,2, software:2.2&gt;" unit="count/min" creationDate="2016-04-16 10:47:10 -0300" startDate="2016-04-16 10:47:10 -0300" endDate="2016-04-16 10:47:10 -0300" value="59"/>
 <Record type="HKQuantityTypeIdentifierHeartRate" sourceName="Nicolas's Apple Watch" sourceVersion="2.2" device="&lt;&lt;HKDevice: 0x145b66220&gt;, name:Apple Watch, manufacturer:Apple, model:Watch, hardware:Watch1,2, software:2.2&gt;" unit="count/min" creationDate="2016-04-16 10:47:16 -0300" startDate="2016-04-16 10:47:15 -0300" endDate="2016-04-16 10:47:15 -0300" value="58"/>
 <Record type="HKQuantityTypeIdentifierHeartRate" sourceName="Nicolas's Apple Watch" sourceVersion="2.2" device="&lt;&lt;HKDevice: 0x145b66480&gt;, name:Apple Watch, manufacturer:Apple, model:Watch, hardware:Watch1,2, software:2.2&gt;" unit="count/min" creationDate="2016-04-16 10:47:21 -0300" startDate="2016-04-16 10:47:20 -0300" endDate="2016-04-16 10:47:20 -0300" value="59"/>
 <Record type="HKQuantityTypeIdentifierHeartRate" sourceName="Nicolas's Apple Watch" sourceVersion="2.2" device="&lt;&lt;HKDevice: 0x145b666e0&gt;, name:Apple Watch, manufacturer:Apple, model:Watch, hardware:Watch1,2, software:2.2&gt;" unit="count/min" creationDate="2016-04-16 10:47:25 -0300" startDate="2016-04-16 10:47:25 -0300" endDate="2016-04-16 10:47:25 -0300" value="59"/>
 <Record type="HKQuantityTypeIdentifierHeartRate" sourceName="Nicolas's Apple Watch" sourceVersion="2.2" device="&lt;&lt;HKDevice: 0x145b66940&gt;, name:Apple Watch, manufacturer:Apple, model:Watch, hardware:Watch1,2, software:2.2&gt;" unit="count/min" creationDate="2016-04-16 10:47:30 -0300" startDate="2016-04-16 10:47:30 -0300" endDate="2016-04-16 10:47:30 -0300" value="64"/>
 <Record type="HKQuantityTypeIdentifierHeartRate" sourceName="Nicolas's Apple Watch" sourceVersion="2.2" device="&lt;&lt;HKDevice: 0x145b66ba0&gt;, name:Apple Watch, manufacturer:Apple, model:Watch, hardware:Watch1,2, software:2.2&gt;" unit="count/min" creationDate="2016-04-16 10:47:35 -0300" startDate="2016-04-16 10:47:35 -0300" endDate="2016-04-16 10:47:35 -0300" value="65"/>
 <Record type="HKQuantityTypeIdentifierHeartRate" sourceName="Nicolas's Apple Watch" sourceVersion="2.2" device="&lt;&lt;HKDevice: 0x145b66e00&gt;, name:Apple Watch, manufacturer:Apple, model:Watch, hardware:Watch1,2, software:2.2&gt;" unit="count/min" creationDate="2016-04-16 10:47:40 -0300" startDate="2016-04-16 10:47:40 -0300" endDate="2016-04-16 10:47:40 -0300" value="72"/>
 <Record type="HKQuantityTypeIdentifierHeartRate" sourceName="Nicolas's Apple Watch" sourceVersion="2.2" device="&lt;&lt;HKDevice: 0x145b67060&gt;, name:Apple Watch, manufacturer:Apple, model:Watch, hardware:Watch1,2, software:2.2&gt;" unit="count/min" creationDate="2016-04-16 10:47:45 -0300" startDate="2016-04-16 10:47:45 -0300" endDate="2016-04-16 10:47:45 -0300" value="74"/>
 <Record type="HKQuantityTypeIdentifierHeartRate" sourceName="Nicolas's Apple Watch" sourceVersion="2.2" device="&lt;&lt;HKDevice: 0x145b672c0&gt;, name:Apple Watch, manufacturer:Apple, model:Watch, hardware:Watch1,2, software:2.2&gt;" unit="count/min" creationDate="2016-04-16 10:47:50 -0300" startDate="2016-04-16 10:47:50 -0300" endDate="2016-04-16 10:47:50 -0300" value="74"/>
 <Record type="HKQuantityTypeIdentifierHeartRate" sourceName="Nicolas's Apple Watch" sourceVersion="2.2" device="&lt;&lt;HKDevice: 0x145b67520&gt;, name:Apple Watch, manufacturer:Apple, model:Watch, hardware:Watch1,2, software:2.2&gt;" unit="count/min" creationDate="2016-04-16 10:47:55 -0300" startDate="2016-04-16 10:47:55 -0300" endDate="2016-04-16 10:47:55 -0300" value="74"/>
 <Record type="HKQuantityTypeIdentifierHeartRate" sourceName="Nicolas's Apple Watch" sourceVersion="2.2" device="&lt;&lt;HKDevice: 0x145b67780&gt;, name:Apple Watch, manufacturer:Apple, model:Watch, hardware:Watch1,2, software:2.2&gt;" unit="count/min" creationDate="2016-04-16 10:48:00 -0300" startDate="2016-04-16 10:48:00 -0300" endDate="2016-04-16 10:48:00 -0300" value="74"/>
 <Record type="HKQuantityTypeIdentifierHeartRate" sourceName="Nicolas's Apple Watch" sourceVersion="2.2" device="&lt;&lt;HKDevice: 0x145b679e0&gt;, name:Apple Watch, manufacturer:Apple, model:Watch, hardware:Watch1,2, software:2.2&gt;" unit="count/min" creationDate="2016-04-16 10:48:05 -0300" startDate="2016-04-16 10:48:05 -0300" endDate="2016-04-16 10:48:05 -0300" value="73"/>
 <Record type="HKQuantityTypeIdentifierHeartRate" sourceName="Nicolas's Apple Watch" sourceVersion="2.2" device="&lt;&lt;HKDevice: 0x145b67c40&gt;, name:Apple Watch, manufacturer:Apple, model:Watch, hardware:Watch1,2, software:2.2&gt;" unit="count/min" creationDate="2016-04-16 10:48:20 -0300" startDate="2016-04-16 10:48:20 -0300" endDate="2016-04-16 10:48:20 -0300" value="74"/>
 <Record type="HKQuantityTypeIdentifierHeartRate" sourceName="Nicolas's Apple Watch" sourceVersion="2.2" device="&lt;&lt;HKDevice: 0x145b67ea0&gt;, name:Apple Watch, manufacturer:Apple, model:Watch, hardware:Watch1,2, software:2.2&gt;" unit="count/min" creationDate="2016-04-16 10:48:40 -0300" startDate="2016-04-16 10:48:40 -0300" endDate="2016-04-16 10:48:40 -0300" value="59"/>
 <Record type="HKQuantityTypeIdentifierHeartRate" sourceName="Nicolas's Apple Watch" sourceVersion="2.2" device="&lt;&lt;HKDevice: 0x145b68100&gt;, name:Apple Watch, manufacturer:Apple, model:Watch, hardware:Watch1,2, software:2.2&gt;" unit="count/min" creationDate="2016-04-16 10:48:45 -0300" startDate="2016-04-16 10:48:45 -0300" endDate="2016-04-16 10:48:45 -0300" value="59"/>
 <Record type="HKQuantityTypeIdentifierHeartRate" sourceName="Nicolas's Apple Watch" sourceVersion="2.2" device="&lt;&lt;HKDevice: 0x145b68360&gt;, name:Apple Watch, manufacturer:Apple, model:Watch, hardware:Watch1,2, software:2.2&gt;" unit="count/min" creationDate="2016-04-16 10:48:50 -0300" startDate="2016-04-16 10:48:50 -0300" endDate="2016-04-16 10:48:50 -0300" value="59"/>
 <Record type="HKQuantityTypeIdentifierHeartRate" sourceName="Nicolas's Apple Watch" sourceVersion="2.2" device="&lt;&lt;HKDevice: 0x145b685c0&gt;, name:Apple Watch, manufacturer:Apple, model:Watch, hardware:Watch1,2, software:2.2&gt;" unit="count/min" creationDate="2016-04-16 10:48:55 -0300" startDate="2016-04-16 10:48:55 -0300" endDate="2016-04-16 10:48:55 -0300" value="59"/>
 <Record type="HKQuantityTypeIdentifierHeartRate" sourceName="Nicolas's Apple Watch" sourceVersion="2.2" device="&lt;&lt;HKDevice: 0x145b68820&gt;, name:Apple Watch, manufacturer:Apple, model:Watch, hardware:Watch1,2, software:2.2&gt;" unit="count/min" creationDate="2016-04-16 10:49:00 -0300" startDate="2016-04-16 10:49:00 -0300" endDate="2016-04-16 10:49:00 -0300" value="59"/>
 <Record type="HKQuantityTypeIdentifierHeartRate" sourceName="Nicolas's Apple Watch" sourceVersion="2.2" device="&lt;&lt;HKDevice: 0x145b68a80&gt;, name:Apple Watch, manufacturer:Apple, model:Watch, hardware:Watch1,2, software:2.2&gt;" unit="count/min" creationDate="2016-04-16 10:49:05 -0300" startDate="2016-04-16 10:49:05 -0300" endDate="2016-04-16 10:49:05 -0300" value="59"/>
 <Record type="HKQuantityTypeIdentifierHeartRate" sourceName="Nicolas's Apple Watch" sourceVersion="2.2" device="&lt;&lt;HKDevice: 0x145b68ce0&gt;, name:Apple Watch, manufacturer:Apple, model:Watch, hardware:Watch1,2, software:2.2&gt;" unit="count/min" creationDate="2016-04-16 10:49:10 -0300" startDate="2016-04-16 10:49:10 -0300" endDate="2016-04-16 10:49:10 -0300" value="59"/>
 <Record type="HKQuantityTypeIdentifierHeartRate" sourceName="Nicolas's Apple Watch" sourceVersion="2.2" device="&lt;&lt;HKDevice: 0x145b68f40&gt;, name:Apple Watch, manufacturer:Apple, model:Watch, hardware:Watch1,2, software:2.2&gt;" unit="count/min" creationDate="2016-04-16 10:49:15 -0300" startDate="2016-04-16 10:49:15 -0300" endDate="2016-04-16 10:49:15 -0300" value="59"/>
 <Record type="HKQuantityTypeIdentifierHeartRate" sourceName="Nicolas's Apple Watch" sourceVersion="2.2" device="&lt;&lt;HKDevice: 0x145b691a0&gt;, name:Apple Watch, manufacturer:Apple, model:Watch, hardware:Watch1,2, software:2.2&gt;" unit="count/min" creationDate="2016-04-16 10:51:06 -0300" startDate="2016-04-16 10:51:05 -0300" endDate="2016-04-16 10:51:05 -0300" value="72"/>
 <Record type="HKQuantityTypeIdentifierHeartRate" sourceName="Nicolas's Apple Watch" sourceVersion="2.2" device="&lt;&lt;HKDevice: 0x145b69400&gt;, name:Apple Watch, manufacturer:Apple, model:Watch, hardware:Watch1,2, software:2.2&gt;" unit="count/min" creationDate="2016-04-16 10:51:11 -0300" startDate="2016-04-16 10:51:10 -0300" endDate="2016-04-16 10:51:10 -0300" value="72"/>
 <Record type="HKQuantityTypeIdentifierHeartRate" sourceName="Nicolas's Apple Watch" sourceVersion="2.2" device="&lt;&lt;HKDevice: 0x145b69660&gt;, name:Apple Watch, manufacturer:Apple, model:Watch, hardware:Watch1,2, software:2.2&gt;" unit="count/min" creationDate="2016-04-16 10:51:15 -0300" startDate="2016-04-16 10:51:15 -0300" endDate="2016-04-16 10:51:15 -0300" value="72"/>
 <Record type="HKQuantityTypeIdentifierHeartRate" sourceName="Nicolas's Apple Watch" sourceVersion="2.2" device="&lt;&lt;HKDevice: 0x145b698c0&gt;, name:Apple Watch, manufacturer:Apple, model:Watch, hardware:Watch1,2, software:2.2&gt;" unit="count/min" creationDate="2016-04-16 10:51:45 -0300" startDate="2016-04-16 10:51:45 -0300" endDate="2016-04-16 10:51:45 -0300" value="103"/>
 <Record type="HKQuantityTypeIdentifierHeartRate" sourceName="Nicolas's Apple Watch" sourceVersion="2.2" device="&lt;&lt;HKDevice: 0x145b69b20&gt;, name:Apple Watch, manufacturer:Apple, model:Watch, hardware:Watch1,2, software:2.2&gt;" unit="count/min" creationDate="2016-04-16 10:52:25 -0300" startDate="2016-04-16 10:52:25 -0300" endDate="2016-04-16 10:52:25 -0300" value="63"/>
 <Record type="HKQuantityTypeIdentifierHeartRate" sourceName="Nicolas's Apple Watch" sourceVersion="2.2" device="&lt;&lt;HKDevice: 0x145b69d80&gt;, name:Apple Watch, manufacturer:Apple, model:Watch, hardware:Watch1,2, software:2.2&gt;" unit="count/min" creationDate="2016-04-16 10:52:30 -0300" startDate="2016-04-16 10:52:30 -0300" endDate="2016-04-16 10:52:30 -0300" value="63"/>
 <Record type="HKQuantityTypeIdentifierHeartRate" sourceName="Nicolas's Apple Watch" sourceVersion="2.2" device="&lt;&lt;HKDevice: 0x145b69fe0&gt;, name:Apple Watch, manufacturer:Apple, model:Watch, hardware:Watch1,2, software:2.2&gt;" unit="count/min" creationDate="2016-04-16 10:52:35 -0300" startDate="2016-04-16 10:52:35 -0300" endDate="2016-04-16 10:52:35 -0300" value="63"/>
 <Record type="HKQuantityTypeIdentifierHeartRate" sourceName="Nicolas's Apple Watch" sourceVersion="2.2" device="&lt;&lt;HKDevice: 0x145b6a240&gt;, name:Apple Watch, manufacturer:Apple, model:Watch, hardware:Watch1,2, software:2.2&gt;" unit="count/min" creationDate="2016-04-16 10:54:50 -0300" startDate="2016-04-16 10:54:50 -0300" endDate="2016-04-16 10:54:50 -0300" value="74"/>
 <Record type="HKQuantityTypeIdentifierHeartRate" sourceName="Nicolas's Apple Watch" sourceVersion="2.2" device="&lt;&lt;HKDevice: 0x145b6a4a0&gt;, name:Apple Watch, manufacturer:Apple, model:Watch, hardware:Watch1,2, software:2.2&gt;" unit="count/min" creationDate="2016-04-16 10:54:55 -0300" startDate="2016-04-16 10:54:55 -0300" endDate="2016-04-16 10:54:55 -0300" value="76"/>
 <Record type="HKQuantityTypeIdentifierHeartRate" sourceName="Nicolas's Apple Watch" sourceVersion="2.2" device="&lt;&lt;HKDevice: 0x145b6a700&gt;, name:Apple Watch, manufacturer:Apple, model:Watch, hardware:Watch1,2, software:2.2&gt;" unit="count/min" creationDate="2016-04-16 10:55:00 -0300" startDate="2016-04-16 10:55:00 -0300" endDate="2016-04-16 10:55:00 -0300" value="77"/>
 <Record type="HKQuantityTypeIdentifierHeartRate" sourceName="Nicolas's Apple Watch" sourceVersion="2.2" device="&lt;&lt;HKDevice: 0x145b6a960&gt;, name:Apple Watch, manufacturer:Apple, model:Watch, hardware:Watch1,2, software:2.2&gt;" unit="count/min" creationDate="2016-04-16 10:55:05 -0300" startDate="2016-04-16 10:55:05 -0300" endDate="2016-04-16 10:55:05 -0300" value="77"/>
 <Record type="HKQuantityTypeIdentifierHeartRate" sourceName="Nicolas's Apple Watch" sourceVersion="2.2" device="&lt;&lt;HKDevice: 0x145b6abc0&gt;, name:Apple Watch, manufacturer:Apple, model:Watch, hardware:Watch1,2, software:2.2&gt;" unit="count/min" creationDate="2016-04-16 10:55:10 -0300" startDate="2016-04-16 10:55:10 -0300" endDate="2016-04-16 10:55:10 -0300" value="77"/>
 <Record type="HKQuantityTypeIdentifierHeartRate" sourceName="Nicolas's Apple Watch" sourceVersion="2.2" device="&lt;&lt;HKDevice: 0x145b6ae20&gt;, name:Apple Watch, manufacturer:Apple, model:Watch, hardware:Watch1,2, software:2.2&gt;" unit="count/min" creationDate="2016-04-16 10:55:15 -0300" startDate="2016-04-16 10:55:15 -0300" endDate="2016-04-16 10:55:15 -0300" value="77"/>
 <Record type="HKQuantityTypeIdentifierHeartRate" sourceName="Nicolas's Apple Watch" sourceVersion="2.2" device="&lt;&lt;HKDevice: 0x145b6b080&gt;, name:Apple Watch, manufacturer:Apple, model:Watch, hardware:Watch1,2, software:2.2&gt;" unit="count/min" creationDate="2016-04-16 10:56:55 -0300" startDate="2016-04-16 10:56:55 -0300" endDate="2016-04-16 10:56:55 -0300" value="53"/>
 <Record type="HKQuantityTypeIdentifierHeartRate" sourceName="Nicolas's Apple Watch" sourceVersion="2.2" device="&lt;&lt;HKDevice: 0x145b6b2e0&gt;, name:Apple Watch, manufacturer:Apple, model:Watch, hardware:Watch1,2, software:2.2&gt;" unit="count/min" creationDate="2016-04-16 10:58:40 -0300" startDate="2016-04-16 10:58:40 -0300" endDate="2016-04-16 10:58:40 -0300" value="59"/>
 <Record type="HKQuantityTypeIdentifierHeartRate" sourceName="Nicolas's Apple Watch" sourceVersion="2.2" device="&lt;&lt;HKDevice: 0x145b6b540&gt;, name:Apple Watch, manufacturer:Apple, model:Watch, hardware:Watch1,2, software:2.2&gt;" unit="count/min" creationDate="2016-04-16 10:58:45 -0300" startDate="2016-04-16 10:58:45 -0300" endDate="2016-04-16 10:58:45 -0300" value="60"/>
 <Record type="HKQuantityTypeIdentifierHeartRate" sourceName="Nicolas's Apple Watch" sourceVersion="2.2" device="&lt;&lt;HKDevice: 0x145b6b7a0&gt;, name:Apple Watch, manufacturer:Apple, model:Watch, hardware:Watch1,2, software:2.2&gt;" unit="count/min" creationDate="2016-04-16 10:58:50 -0300" startDate="2016-04-16 10:58:50 -0300" endDate="2016-04-16 10:58:50 -0300" value="63"/>
 <Record type="HKQuantityTypeIdentifierHeartRate" sourceName="Nicolas's Apple Watch" sourceVersion="2.2" device="&lt;&lt;HKDevice: 0x145b6ba00&gt;, name:Apple Watch, manufacturer:Apple, model:Watch, hardware:Watch1,2, software:2.2&gt;" unit="count/min" creationDate="2016-04-16 10:58:55 -0300" startDate="2016-04-16 10:58:55 -0300" endDate="2016-04-16 10:58:55 -0300" value="65"/>
 <Record type="HKQuantityTypeIdentifierHeartRate" sourceName="Nicolas's Apple Watch" sourceVersion="2.2" device="&lt;&lt;HKDevice: 0x145b6bc60&gt;, name:Apple Watch, manufacturer:Apple, model:Watch, hardware:Watch1,2, software:2.2&gt;" unit="count/min" creationDate="2016-04-16 10:59:05 -0300" startDate="2016-04-16 10:59:05 -0300" endDate="2016-04-16 10:59:05 -0300" value="64"/>
 <Record type="HKQuantityTypeIdentifierHeartRate" sourceName="Nicolas's Apple Watch" sourceVersion="2.2" device="&lt;&lt;HKDevice: 0x145b6bec0&gt;, name:Apple Watch, manufacturer:Apple, model:Watch, hardware:Watch1,2, software:2.2&gt;" unit="count/min" creationDate="2016-04-16 10:59:10 -0300" startDate="2016-04-16 10:59:10 -0300" endDate="2016-04-16 10:59:10 -0300" value="64"/>
 <Record type="HKQuantityTypeIdentifierHeartRate" sourceName="Nicolas's Apple Watch" sourceVersion="2.2" device="&lt;&lt;HKDevice: 0x145b6c120&gt;, name:Apple Watch, manufacturer:Apple, model:Watch, hardware:Watch1,2, software:2.2&gt;" unit="count/min" creationDate="2016-04-16 10:59:15 -0300" startDate="2016-04-16 10:59:15 -0300" endDate="2016-04-16 10:59:15 -0300" value="53"/>
 <Record type="HKQuantityTypeIdentifierHeartRate" sourceName="Nicolas's Apple Watch" sourceVersion="2.2" device="&lt;&lt;HKDevice: 0x145b6c380&gt;, name:Apple Watch, manufacturer:Apple, model:Watch, hardware:Watch1,2, software:2.2&gt;" unit="count/min" creationDate="2016-04-16 10:59:45 -0300" startDate="2016-04-16 10:59:45 -0300" endDate="2016-04-16 10:59:45 -0300" value="125"/>
 <Record type="HKQuantityTypeIdentifierHeartRate" sourceName="Nicolas's Apple Watch" sourceVersion="2.2" device="&lt;&lt;HKDevice: 0x145b6c5e0&gt;, name:Apple Watch, manufacturer:Apple, model:Watch, hardware:Watch1,2, software:2.2&gt;" unit="count/min" creationDate="2016-04-16 10:59:50 -0300" startDate="2016-04-16 10:59:50 -0300" endDate="2016-04-16 10:59:50 -0300" value="123"/>
 <Record type="HKQuantityTypeIdentifierHeartRate" sourceName="Nicolas's Apple Watch" sourceVersion="2.2" device="&lt;&lt;HKDevice: 0x140ca3c90&gt;, name:Apple Watch, manufacturer:Apple, model:Watch, hardware:Watch1,2, software:2.2&gt;" unit="count/min" creationDate="2016-04-16 10:59:55 -0300" startDate="2016-04-16 10:59:55 -0300" endDate="2016-04-16 10:59:55 -0300" value="123"/>
 <Record type="HKQuantityTypeIdentifierHeartRate" sourceName="Nicolas's Apple Watch" sourceVersion="2.2" device="&lt;&lt;HKDevice: 0x140ca3ef0&gt;, name:Apple Watch, manufacturer:Apple, model:Watch, hardware:Watch1,2, software:2.2&gt;" unit="count/min" creationDate="2016-04-16 11:00:01 -0300" startDate="2016-04-16 11:00:00 -0300" endDate="2016-04-16 11:00:00 -0300" value="120"/>
 <Record type="HKQuantityTypeIdentifierHeartRate" sourceName="Nicolas's Apple Watch" sourceVersion="2.2" device="&lt;&lt;HKDevice: 0x140ca4150&gt;, name:Apple Watch, manufacturer:Apple, model:Watch, hardware:Watch1,2, software:2.2&gt;" unit="count/min" creationDate="2016-04-16 11:00:05 -0300" startDate="2016-04-16 11:00:05 -0300" endDate="2016-04-16 11:00:05 -0300" value="120"/>
 <Record type="HKQuantityTypeIdentifierHeartRate" sourceName="Nicolas's Apple Watch" sourceVersion="2.2" device="&lt;&lt;HKDevice: 0x140ca4910&gt;, name:Apple Watch, manufacturer:Apple, model:Watch, hardware:Watch1,2, software:2.2&gt;" unit="count/min" creationDate="2016-04-16 11:00:10 -0300" startDate="2016-04-16 11:00:10 -0300" endDate="2016-04-16 11:00:10 -0300" value="119"/>
 <Record type="HKQuantityTypeIdentifierHeartRate" sourceName="Nicolas's Apple Watch" sourceVersion="2.2" device="&lt;&lt;HKDevice: 0x140ca49e0&gt;, name:Apple Watch, manufacturer:Apple, model:Watch, hardware:Watch1,2, software:2.2&gt;" unit="count/min" creationDate="2016-04-16 11:00:15 -0300" startDate="2016-04-16 11:00:15 -0300" endDate="2016-04-16 11:00:15 -0300" value="114"/>
 <Record type="HKQuantityTypeIdentifierHeartRate" sourceName="Nicolas's Apple Watch" sourceVersion="2.2" device="&lt;&lt;HKDevice: 0x140ca4b70&gt;, name:Apple Watch, manufacturer:Apple, model:Watch, hardware:Watch1,2, software:2.2&gt;" unit="count/min" creationDate="2016-04-16 11:00:20 -0300" startDate="2016-04-16 11:00:20 -0300" endDate="2016-04-16 11:00:20 -0300" value="114"/>
 <Record type="HKQuantityTypeIdentifierHeartRate" sourceName="Nicolas's Apple Watch" sourceVersion="2.2" device="&lt;&lt;HKDevice: 0x140ca4cf0&gt;, name:Apple Watch, manufacturer:Apple, model:Watch, hardware:Watch1,2, software:2.2&gt;" unit="count/min" creationDate="2016-04-16 11:00:25 -0300" startDate="2016-04-16 11:00:25 -0300" endDate="2016-04-16 11:00:25 -0300" value="113"/>
 <Record type="HKQuantityTypeIdentifierHeartRate" sourceName="Nicolas's Apple Watch" sourceVersion="2.2" device="&lt;&lt;HKDevice: 0x140ca4e80&gt;, name:Apple Watch, manufacturer:Apple, model:Watch, hardware:Watch1,2, software:2.2&gt;" unit="count/min" creationDate="2016-04-16 11:00:30 -0300" startDate="2016-04-16 11:00:30 -0300" endDate="2016-04-16 11:00:30 -0300" value="109"/>
 <Record type="HKQuantityTypeIdentifierHeartRate" sourceName="Nicolas's Apple Watch" sourceVersion="2.2" device="&lt;&lt;HKDevice: 0x140ca5030&gt;, name:Apple Watch, manufacturer:Apple, model:Watch, hardware:Watch1,2, software:2.2&gt;" unit="count/min" creationDate="2016-04-16 11:00:35 -0300" startDate="2016-04-16 11:00:35 -0300" endDate="2016-04-16 11:00:35 -0300" value="109"/>
 <Record type="HKQuantityTypeIdentifierHeartRate" sourceName="Nicolas's Apple Watch" sourceVersion="2.2" device="&lt;&lt;HKDevice: 0x140ca51c0&gt;, name:Apple Watch, manufacturer:Apple, model:Watch, hardware:Watch1,2, software:2.2&gt;" unit="count/min" creationDate="2016-04-16 11:00:40 -0300" startDate="2016-04-16 11:00:40 -0300" endDate="2016-04-16 11:00:40 -0300" value="119"/>
 <Record type="HKQuantityTypeIdentifierHeartRate" sourceName="Nicolas's Apple Watch" sourceVersion="2.2" device="&lt;&lt;HKDevice: 0x140ca53a0&gt;, name:Apple Watch, manufacturer:Apple, model:Watch, hardware:Watch1,2, software:2.2&gt;" unit="count/min" creationDate="2016-04-16 11:00:45 -0300" startDate="2016-04-16 11:00:45 -0300" endDate="2016-04-16 11:00:45 -0300" value="118"/>
 <Record type="HKQuantityTypeIdentifierHeartRate" sourceName="Nicolas's Apple Watch" sourceVersion="2.2" device="&lt;&lt;HKDevice: 0x140ca54f0&gt;, name:Apple Watch, manufacturer:Apple, model:Watch, hardware:Watch1,2, software:2.2&gt;" unit="count/min" creationDate="2016-04-16 11:00:50 -0300" startDate="2016-04-16 11:00:50 -0300" endDate="2016-04-16 11:00:50 -0300" value="118"/>
 <Record type="HKQuantityTypeIdentifierHeartRate" sourceName="Nicolas's Apple Watch" sourceVersion="2.2" device="&lt;&lt;HKDevice: 0x140ca5680&gt;, name:Apple Watch, manufacturer:Apple, model:Watch, hardware:Watch1,2, software:2.2&gt;" unit="count/min" creationDate="2016-04-16 11:00:55 -0300" startDate="2016-04-16 11:00:55 -0300" endDate="2016-04-16 11:00:55 -0300" value="119"/>
 <Record type="HKQuantityTypeIdentifierHeartRate" sourceName="Nicolas's Apple Watch" sourceVersion="2.2" device="&lt;&lt;HKDevice: 0x140ca5810&gt;, name:Apple Watch, manufacturer:Apple, model:Watch, hardware:Watch1,2, software:2.2&gt;" unit="count/min" creationDate="2016-04-16 11:01:00 -0300" startDate="2016-04-16 11:01:00 -0300" endDate="2016-04-16 11:01:00 -0300" value="119"/>
 <Record type="HKQuantityTypeIdentifierHeartRate" sourceName="Nicolas's Apple Watch" sourceVersion="2.2" device="&lt;&lt;HKDevice: 0x140ca59c0&gt;, name:Apple Watch, manufacturer:Apple, model:Watch, hardware:Watch1,2, software:2.2&gt;" unit="count/min" creationDate="2016-04-16 11:01:15 -0300" startDate="2016-04-16 11:01:15 -0300" endDate="2016-04-16 11:01:15 -0300" value="106"/>
 <Record type="HKQuantityTypeIdentifierHeartRate" sourceName="Nicolas's Apple Watch" sourceVersion="2.2" device="&lt;&lt;HKDevice: 0x140ca5b50&gt;, name:Apple Watch, manufacturer:Apple, model:Watch, hardware:Watch1,2, software:2.2&gt;" unit="count/min" creationDate="2016-04-16 11:01:20 -0300" startDate="2016-04-16 11:01:20 -0300" endDate="2016-04-16 11:01:20 -0300" value="108"/>
 <Record type="HKQuantityTypeIdentifierHeartRate" sourceName="Nicolas's Apple Watch" sourceVersion="2.2" device="&lt;&lt;HKDevice: 0x140ca5ce0&gt;, name:Apple Watch, manufacturer:Apple, model:Watch, hardware:Watch1,2, software:2.2&gt;" unit="count/min" creationDate="2016-04-16 11:01:25 -0300" startDate="2016-04-16 11:01:25 -0300" endDate="2016-04-16 11:01:25 -0300" value="108"/>
 <Record type="HKQuantityTypeIdentifierHeartRate" sourceName="Nicolas's Apple Watch" sourceVersion="2.2" device="&lt;&lt;HKDevice: 0x140ca5e70&gt;, name:Apple Watch, manufacturer:Apple, model:Watch, hardware:Watch1,2, software:2.2&gt;" unit="count/min" creationDate="2016-04-16 11:01:30 -0300" startDate="2016-04-16 11:01:30 -0300" endDate="2016-04-16 11:01:30 -0300" value="108"/>
 <Record type="HKQuantityTypeIdentifierHeartRate" sourceName="Nicolas's Apple Watch" sourceVersion="2.2" device="&lt;&lt;HKDevice: 0x140ca6000&gt;, name:Apple Watch, manufacturer:Apple, model:Watch, hardware:Watch1,2, software:2.2&gt;" unit="count/min" creationDate="2016-04-16 11:01:35 -0300" startDate="2016-04-16 11:01:35 -0300" endDate="2016-04-16 11:01:35 -0300" value="109"/>
 <Record type="HKQuantityTypeIdentifierHeartRate" sourceName="Nicolas's Apple Watch" sourceVersion="2.2" device="&lt;&lt;HKDevice: 0x145b510d0&gt;, name:Apple Watch, manufacturer:Apple, model:Watch, hardware:Watch1,2, software:2.2&gt;" unit="count/min" creationDate="2016-04-16 11:01:40 -0300" startDate="2016-04-16 11:01:40 -0300" endDate="2016-04-16 11:01:40 -0300" value="110"/>
 <Record type="HKQuantityTypeIdentifierHeartRate" sourceName="Nicolas's Apple Watch" sourceVersion="2.2" device="&lt;&lt;HKDevice: 0x145b51330&gt;, name:Apple Watch, manufacturer:Apple, model:Watch, hardware:Watch1,2, software:2.2&gt;" unit="count/min" creationDate="2016-04-16 11:01:45 -0300" startDate="2016-04-16 11:01:45 -0300" endDate="2016-04-16 11:01:45 -0300" value="108"/>
 <Record type="HKQuantityTypeIdentifierHeartRate" sourceName="Nicolas's Apple Watch" sourceVersion="2.2" device="&lt;&lt;HKDevice: 0x145b514c0&gt;, name:Apple Watch, manufacturer:Apple, model:Watch, hardware:Watch1,2, software:2.2&gt;" unit="count/min" creationDate="2016-04-16 11:01:50 -0300" startDate="2016-04-16 11:01:50 -0300" endDate="2016-04-16 11:01:50 -0300" value="107"/>
 <Record type="HKQuantityTypeIdentifierHeartRate" sourceName="Nicolas's Apple Watch" sourceVersion="2.2" device="&lt;&lt;HKDevice: 0x145b6c720&gt;, name:Apple Watch, manufacturer:Apple, model:Watch, hardware:Watch1,2, software:2.2&gt;" unit="count/min" creationDate="2016-04-16 11:01:55 -0300" startDate="2016-04-16 11:01:55 -0300" endDate="2016-04-16 11:01:55 -0300" value="108"/>
 <Record type="HKQuantityTypeIdentifierHeartRate" sourceName="Nicolas's Apple Watch" sourceVersion="2.2" device="&lt;&lt;HKDevice: 0x145b6c8b0&gt;, name:Apple Watch, manufacturer:Apple, model:Watch, hardware:Watch1,2, software:2.2&gt;" unit="count/min" creationDate="2016-04-16 11:02:00 -0300" startDate="2016-04-16 11:02:00 -0300" endDate="2016-04-16 11:02:00 -0300" value="108"/>
 <Record type="HKQuantityTypeIdentifierHeartRate" sourceName="Nicolas's Apple Watch" sourceVersion="2.2" device="&lt;&lt;HKDevice: 0x145b6ca40&gt;, name:Apple Watch, manufacturer:Apple, model:Watch, hardware:Watch1,2, software:2.2&gt;" unit="count/min" creationDate="2016-04-16 11:02:05 -0300" startDate="2016-04-16 11:02:05 -0300" endDate="2016-04-16 11:02:05 -0300" value="106"/>
 <Record type="HKQuantityTypeIdentifierHeartRate" sourceName="Nicolas's Apple Watch" sourceVersion="2.2" device="&lt;&lt;HKDevice: 0x145b6cbd0&gt;, name:Apple Watch, manufacturer:Apple, model:Watch, hardware:Watch1,2, software:2.2&gt;" unit="count/min" creationDate="2016-04-16 11:02:10 -0300" startDate="2016-04-16 11:02:10 -0300" endDate="2016-04-16 11:02:10 -0300" value="106"/>
 <Record type="HKQuantityTypeIdentifierHeartRate" sourceName="Nicolas's Apple Watch" sourceVersion="2.2" device="&lt;&lt;HKDevice: 0x145b6cd60&gt;, name:Apple Watch, manufacturer:Apple, model:Watch, hardware:Watch1,2, software:2.2&gt;" unit="count/min" creationDate="2016-04-16 11:02:15 -0300" startDate="2016-04-16 11:02:15 -0300" endDate="2016-04-16 11:02:15 -0300" value="105"/>
 <Record type="HKQuantityTypeIdentifierHeartRate" sourceName="Nicolas's Apple Watch" sourceVersion="2.2" device="&lt;&lt;HKDevice: 0x145b6cef0&gt;, name:Apple Watch, manufacturer:Apple, model:Watch, hardware:Watch1,2, software:2.2&gt;" unit="count/min" creationDate="2016-04-16 11:02:20 -0300" startDate="2016-04-16 11:02:20 -0300" endDate="2016-04-16 11:02:20 -0300" value="106"/>
 <Record type="HKQuantityTypeIdentifierHeartRate" sourceName="Nicolas's Apple Watch" sourceVersion="2.2" device="&lt;&lt;HKDevice: 0x145b6d080&gt;, name:Apple Watch, manufacturer:Apple, model:Watch, hardware:Watch1,2, software:2.2&gt;" unit="count/min" creationDate="2016-04-16 11:02:25 -0300" startDate="2016-04-16 11:02:25 -0300" endDate="2016-04-16 11:02:25 -0300" value="104"/>
 <Record type="HKQuantityTypeIdentifierHeartRate" sourceName="Nicolas's Apple Watch" sourceVersion="2.2" device="&lt;&lt;HKDevice: 0x145b6d210&gt;, name:Apple Watch, manufacturer:Apple, model:Watch, hardware:Watch1,2, software:2.2&gt;" unit="count/min" creationDate="2016-04-16 11:02:30 -0300" startDate="2016-04-16 11:02:30 -0300" endDate="2016-04-16 11:02:30 -0300" value="108"/>
 <Record type="HKQuantityTypeIdentifierHeartRate" sourceName="Nicolas's Apple Watch" sourceVersion="2.2" device="&lt;&lt;HKDevice: 0x145b6d4e0&gt;, name:Apple Watch, manufacturer:Apple, model:Watch, hardware:Watch1,2, software:2.2&gt;" unit="count/min" creationDate="2016-04-16 11:02:35 -0300" startDate="2016-04-16 11:02:35 -0300" endDate="2016-04-16 11:02:35 -0300" value="108"/>
 <Record type="HKQuantityTypeIdentifierHeartRate" sourceName="Nicolas's Apple Watch" sourceVersion="2.2" device="&lt;&lt;HKDevice: 0x145b6d5b0&gt;, name:Apple Watch, manufacturer:Apple, model:Watch, hardware:Watch1,2, software:2.2&gt;" unit="count/min" creationDate="2016-04-16 11:02:40 -0300" startDate="2016-04-16 11:02:40 -0300" endDate="2016-04-16 11:02:40 -0300" value="107"/>
 <Record type="HKQuantityTypeIdentifierHeartRate" sourceName="Nicolas's Apple Watch" sourceVersion="2.2" device="&lt;&lt;HKDevice: 0x145b6d740&gt;, name:Apple Watch, manufacturer:Apple, model:Watch, hardware:Watch1,2, software:2.2&gt;" unit="count/min" creationDate="2016-04-16 11:02:45 -0300" startDate="2016-04-16 11:02:45 -0300" endDate="2016-04-16 11:02:45 -0300" value="104"/>
 <Record type="HKQuantityTypeIdentifierHeartRate" sourceName="Nicolas's Apple Watch" sourceVersion="2.2" device="&lt;&lt;HKDevice: 0x145b6d8d0&gt;, name:Apple Watch, manufacturer:Apple, model:Watch, hardware:Watch1,2, software:2.2&gt;" unit="count/min" creationDate="2016-04-16 11:02:50 -0300" startDate="2016-04-16 11:02:50 -0300" endDate="2016-04-16 11:02:50 -0300" value="103"/>
 <Record type="HKQuantityTypeIdentifierHeartRate" sourceName="Nicolas's Apple Watch" sourceVersion="2.2" device="&lt;&lt;HKDevice: 0x145b6da60&gt;, name:Apple Watch, manufacturer:Apple, model:Watch, hardware:Watch1,2, software:2.2&gt;" unit="count/min" creationDate="2016-04-16 11:02:55 -0300" startDate="2016-04-16 11:02:55 -0300" endDate="2016-04-16 11:02:55 -0300" value="104"/>
 <Record type="HKQuantityTypeIdentifierHeartRate" sourceName="Nicolas's Apple Watch" sourceVersion="2.2" device="&lt;&lt;HKDevice: 0x145b6dbf0&gt;, name:Apple Watch, manufacturer:Apple, model:Watch, hardware:Watch1,2, software:2.2&gt;" unit="count/min" creationDate="2016-04-16 11:03:00 -0300" startDate="2016-04-16 11:03:00 -0300" endDate="2016-04-16 11:03:00 -0300" value="103"/>
  </HealthData>
